<?xml version="1.0" encoding="UTF-8"?><i><chatserver>chat.bilibili.com</chatserver><chatid>4658752</chatid><mission>0</mission><maxlimit>6000</maxlimit><state>0</state><real_name>0</real_name><source>e-r</source><d p="0.00000,1,25,16777215,1443496275,0,f53fc8e2,1238748390">第一？</d><d p="26.15000,1,25,16777215,1443496278,0,71525839,1238748391">原画就这样马......我可以不带眼镜了</d><d p="9.59400,1,25,16777215,1443496279,0,c193bb4e,1238748392">这画质什么情况？</d><d p="142.90100,1,25,16777215,1443496281,0,c193bb4e,1238748393">当初健完身，公交上车那个台阶硬是半天上不去。。。。</d><d p="5.02800,1,25,16777215,1443496288,0,c973f13f,1238748394">(づ ●─● )づ</d><d p="1002.29000,1,25,16777215,1443496296,0,c193bb4e,1238748395">233</d><d p="86.33800,1,25,16777215,1443496319,0,22a26380,1238748400">2333</d><d p="556.82300,1,25,16777215,1443499922,0,2c01bb89,1238748401">脚贱</d><d p="15.17100,1,25,16777215,1443499925,0,1d6e9a6c,1238748402">画质感人</d><d p="15.91000,1,25,16777215,1443499926,0,5a2f2acb,1238748403">感人的画质</d><d p="38.13700,1,25,16777215,1443499948,0,e99307c4,1238748404">来太早，画质感人</d><d p="281.17600,1,25,16777215,1443499952,0,e99307c4,1238748405">←禁止垂钓</d><d p="940.42300,1,25,16777215,1443499961,0,22a26380,1238748406">1连</d><d p="1916.75000,1,25,16777215,1443499975,0,772fe41b,1238748407">2333</d><d p="10.93600,1,25,16777215,1443499978,0,cbcadb3e,1238748408">AV画质</d><d p="2336.73000,1,25,16777215,1443502866,0,22a26380,1238748409">6使用装</d><d p="530.89900,1,25,16777215,1443502881,0,c8fbc5eb,1238748410">dc</d><d p="1707.00000,1,25,16777215,1443502884,0,f4b25be9,1238748411">撒良辰</d><d p="167.02800,1,25,16777215,1443506562,0,fb438a32,1238821675">菜！</d><d p="20.18700,1,25,16777215,1443506562,0,ab9895a3,1238821959">左下原画</d><d p="278.47200,1,25,16777215,1443506570,0,16830949,1238832411">那就别看啊。</d><d p="116.96000,1,25,16777215,1443506572,0,a2e1760c,1238834117">没人没</d><d p="17.34900,1,25,16777215,1443510204,0,1e3945dd,1238874247">左下原画</d><d p="537.78500,1,25,16777215,1443510212,0,19490049,1238884695">日常黑dc</d><d p="511.08100,1,25,16777215,1443510212,0,19e80eac,1238884945">菜！</d><d p="165.66300,1,25,16777215,1443510228,0,52f54c1e,1238904553">2333</d><d p="1876.54000,1,25,16777215,1443510235,0,19490049,1238914163">全场没眼</d><d p="2404.15000,1,25,16777215,1443513857,0,2f7220c5,1238947473">2333333</d><d p="536.05100,1,25,16777215,1443513868,0,196380d3,1238961591">日常黑DC</d><d p="159.40400,1,25,16777215,1443513871,0,a1f9d883,1238966873">操作不好 </d><d p="1413.17000,1,25,16777215,1443513885,0,a1f9d883,1238985549">打了22分钟 对面一塔未破</d><d p="1677.97000,1,25,16777215,1443513887,0,196380d3,1238988207">nice</d><d p="1629.03000,1,25,16777215,1443513887,0,a1f9d883,1238988857">馊胎</d><d p="1550.87000,1,25,16777215,1443513891,0,b0f7dd43,1238994969">还说不玩do2</d><d p="274.67700,1,25,16777215,1443513894,0,21a81d73,1238999207">←_←那请你圆润地走开别发弹幕扰人清静</d><d p="840.33100,1,25,16777215,1443513898,0,a03479f2,1239004323">牛少等着你补魔呢萌萌</d><d p="517.13200,1,25,16777215,1443513899,0,21a81d73,1239005497">←_←</d><d p="983.61800,1,25,16777215,1443517520,0,6a186ae7,1239036911">不黑  确实有点菜了   波空好多次了</d><d p="532.56700,1,25,16777215,1443517539,0,3e9f7cc3,1239065383">日常黑DC</d><d p="807.64800,1,25,16777215,1443517542,0,54ffaecf,1239070681">猛犸神牛双跳</d><d p="919.30700,1,25,16777215,1443517544,0,54ffaecf,1239073733">三把跳对面报警了</d><d p="942.57700,1,25,16777215,1443517546,0,3e9f7cc3,1239075729">1怎么连</d><d p="281.54500,1,25,16777215,1443517557,0,c02109fe,1239096677">同意，不爱看可以走</d><d p="531.79200,1,25,16777215,1443521161,0,c02109fe,1239103765">日常</d><d p="165.27900,1,25,16777215,1443521164,0,a2cb182c,1239108571">菜</d><d p="290.12600,1,25,16777215,1443521175,0,a653b169,1239128705">同意左边</d><d p="304.06000,1,25,16777215,1443521178,0,c918903f,1239132527">别随便立flag</d><d p="1683.07000,1,25,16777215,1443521179,0,25e064d2,1239135573">这波nice啊</d><d p="14.69000,1,25,16777215,1443521184,0,ee531725,1239145479">左下原画</d><d p="48.71100,5,25,13434624,1443521185,0,ee531725,1239146557">原画</d><d p="50.81100,1,25,16777215,1443521185,0,5e6c5b5,1239146893">人呢</d><d p="273.62100,1,25,16777215,1443521197,0,34266e33,1239169589">撒神没开模式啊</d><d p="505.75200,1,25,16777215,1443521204,0,34266e33,1239184163">flag</d><d p="998.75300,1,25,16777215,1443521213,0,34266e33,1239201469">这个时候应该刷  菜~ 哈哈哈哈</d><d p="1083.04000,1,25,16777215,1443521214,0,34266e33,1239204985">做人不能太贪，然后贪了一个兵</d><d p="1088.38000,1,25,16777215,1443521215,0,34266e33,1239205607">现在有点怂，然后又回去线上了</d><d p="1564.46000,1,25,16777215,1443521215,0,2b8a14d2,1239206141">我一直以为他说的是我的人头 不分赏金</d><d p="1135.78000,1,25,16777215,1443521216,0,34266e33,1239207669">flag</d><d p="279.09600,1,25,16777215,1443524824,0,ed9b9db4,1239225629">←没事找存在感,已举报屏蔽</d><d p="1690.43000,1,25,16777215,1443524825,0,34266e33,1239227997">23333333333</d><d p="1752.34000,1,25,16777215,1443524826,0,34266e33,1239230337">台词被抢233333</d><d p="2073.89900,1,25,16777215,1443524832,0,34266e33,1239242753">nice拱！！</d><d p="48.29500,1,25,16777215,1443524835,0,698420f8,1239250223">人好少啊</d><d p="177.17700,1,25,16777215,1443524839,0,698420f8,1239258189">我赵日天不服</d><d p="507.87100,1,25,16777215,1443524848,0,22c8a43a,1239278883">刚刚不帮你锤了一下了，仁至义尽了啊</d><d p="158.47200,1,25,16777215,1443524851,0,3ff0fa1d,1239286149"> -  - 不管、就是菜丶 23333</d><d p="1786.77000,1,25,16777215,1443524872,0,22c8a43a,1239332431">牛少的flag</d><d p="173.41500,1,25,16777215,1443524873,0,78c2e455,1239336433">一个菜字包含了所有233333</d><d p="13.44400,1,25,16777215,1443524874,0,c728b44,1239338829">左下你懂的</d><d p="41.99500,1,25,16777215,1443524875,0,262c6b01,1239341079">原画+四比三 还行</d><d p="162.58000,1,25,16777215,1443524877,0,262c6b01,1239345731">你什么都菜</d><d p="501.90500,1,25,16777215,1443524879,0,78c2e455,1239349161">个屁啦2333333</d><d p="926.92100,1,25,16777215,1443528489,0,a7738aed,1239371255">这SF真惨= =</d><d p="938.77800,1,25,16777215,1443528494,0,6c04f1fd,1239381583">一连是什么鬼</d><d p="1696.41000,1,25,16777215,1443528505,0,5899941,1239406611">233</d><d p="677.81000,1,25,16777215,1443528506,0,c3bb1e0d,1239409555">一棵吃书都不给</d><d p="142.96500,1,25,16777215,1443528508,0,89467d85,1239413029">完美的漏刀</d><d p="167.60500,1,25,16777215,1443528508,0,89467d85,1239414447">我不管你就是菜哈哈哈哈哈哈</d><d p="226.54500,1,25,16777215,1443528510,0,89467d85,1239417529">说好的不中呢！！</d><d p="2063.03000,1,25,16777215,1443528512,0,6c04f1fd,1239423399">前方高萌</d><d p="541.72500,1,25,16777215,1443528516,0,89467d85,1239431911">尼玛我自从降到60以下后就再没上去过了，坑！！！</d><d p="938.14200,1,25,16777215,1443528523,0,89467d85,1239448129">靠，老子vs你一脸啊</d><d p="34.15700,1,25,16777215,1443532160,0,eb9bb181,1239537591">坐下原画，4:3食用更佳</d><d p="1142.67000,1,25,16777215,1443532160,0,9584572e,1239538393">还是熟悉的萌萌，走哪那没符</d><d p="1376.17000,1,25,16777215,1443532164,0,9584572e,1239547911">吃了一个回复萌萌到现在都没有见过正常的符了</d><d p="1138.24000,1,25,16777215,1443532173,0,c511676f,1239570603">菜</d><d p="1703.08000,1,25,16777215,1443532182,0,cbbde5b1,1239592309">撒良辰</d><d p="2358.08000,1,25,16777215,1443532193,0,cbbde5b1,1239620311">你们这边就a杖小小打塔快</d><d p="2433.12000,1,25,16777215,1443532195,0,cbbde5b1,1239624051">被队友秀了</d><d p="307.17600,1,25,16777215,1443535802,0,eb9bb181,1239640067">禁止垂钓笑哭了</d><d p="772.00000,1,25,16777215,1443535811,0,e25dc235,1239664821">牛少跳刀都比你快</d><d p="2398.10000,1,25,16777215,1443535814,0,89467d85,1239671325">vs调皮了</d><d p="977.94000,1,25,16777215,1443535839,0,bac0632b,1239734397">这不跳上去波？</d><d p="6.87500,1,25,16777215,1443535851,0,24d1559d,1239762651">高产如母猪</d><d p="1453.01000,1,25,16777215,1443535853,0,bac0632b,1239768061"> 不推塔打到后期没优势</d><d p="506.57900,1,25,16777215,1443539472,0,24d1559d,1239815221">flag高高立起</d><d p="1015.07000,1,25,16777215,1443539488,0,352be00d,1239858457">这么菜，我叶良辰单手虐</d><d p="2084.15900,1,25,16777215,1443539492,0,76e76c68,1239867201">cai!!!</d><d p="500.40000,1,25,16777215,1443539496,0,b2ce745c,1239877643">又立flag233</d><d p="1550.31000,1,25,16777215,1443543155,0,61b98994,1239980625">还说你没玩DOTA2</d><d p="2303.03000,1,25,16777215,1443546081,0,ea82b7f8,1240029301">没tp往树林里找干嘛</d><d p="14.21000,1,25,16777215,1443549775,0,31468b00,1240082113">手动4:3</d><d p="170.28300,1,25,16777215,1443553399,0,927ac294,1240090695">其他的我不管 反正你就是菜!</d><d p="1983.58000,1,25,16777215,1443557084,0,956f58d3,1240110951">仁义无双</d><d p="164.03300,1,25,16777215,1443560708,0,a60c9574,1240115613">一个菜字囊括了所有的</d><d p="580.97800,1,25,16777215,1443560715,0,a60c9574,1240116939">吃半个月夜宵就能涨上去了</d><d p="1292.75000,1,25,16777215,1443560726,0,a60c9574,1240119111">我家32层，那个风刮得呼呼的</d><d p="82.48700,1,25,16777215,1443564394,0,61f29ba4,1240131527">  萌萌真菜2333333</d><d p="1451.38000,1,25,16777215,1443564401,0,22bcffe1,1240132979">明明就是你不推</d><d p="2220.65000,1,25,16777215,1443564414,0,22bcffe1,1240135907">全程作用就是给E</d><d p="2291.90000,1,25,16777215,1443564415,0,22bcffe1,1240136157">躺赢</d><d p="2408.00000,1,25,16777215,1443564417,0,22bcffe1,1240136603">又跟你没关系</d><d p="9.45100,1,25,16777215,1443575393,0,4694f328,1240234173">手动4:3</d><d p="489.96200,1,25,16777215,1443579013,0,bdc32159,1240253829">牛哥差点被害死</d><d p="1007.92000,1,25,16777215,1443579033,0,b370aa6c,1240274785">菜233</d><d p="1149.47000,1,25,16777215,1443579035,0,b370aa6c,1240277387">菜</d><d p="535.91600,1,25,16777215,1443582694,0,f280b435,1240345715">DC:我是你爸爸</d><d p="999.62700,1,25,16777215,1443586336,0,fa38fd86,1240399689">菜</d><d p="2358.56000,1,25,16777215,1443586354,0,992aab1f,1240454401">推推也有攻击和攻速啊</d><d p="1010.64000,1,25,16707842,1443589261,0,117bef27,1240515233">没有我接不了的团（锅）。</d><d p="1652.06000,1,25,16777215,1443589267,0,d4c07898,1240528667">说菜的你行你上？</d><d p="1837.60000,1,25,16777215,1443589271,0,d4c07898,1240535375">刚才那波手快点就可以把影魔搞死了</d><d p="2080.15900,1,25,16777215,1443589275,0,d4c07898,1240543349">还是没拱到</d><d p="1164.79000,1,25,16777215,1443589279,0,77055f44,1240551635">刚才小小明明有反应，你却没注意直接走上去，那肯定雪崩啊</d><d p="2019.36000,1,25,16777215,1443589301,0,6b6ffd93,1240594317">小小：天降人头nice</d><d p="166.57800,1,25,16777215,1443592928,0,2c094f82,1240641539">刚刚即补兵不好也操作差</d><d p="290.70900,1,25,16777215,1443592930,0,2c094f82,1240644725">pis忽悠着你</d><d p="711.69100,1,25,16777215,1443592938,0,2c094f82,1240654983">跳跳的</d><d p="861.21800,1,25,16777215,1443592940,0,2c094f82,1240658793">黑人和白人差不多</d><d p="1023.16000,1,25,16777215,1443592943,0,2c094f82,1240662633">但是有接不了的客</d><d p="1305.90000,1,25,16777215,1443592970,0,1e163294,1240702489">耳塞。。</d><d p="709.64000,1,25,16777215,1443592973,0,8c24eb89,1240706839">好活泼23333333</d><d p="977.32000,1,25,16777215,1443592978,0,8c24eb89,1240714421">上路那波杀影魔不放大这波团战随便打的</d><d p="1070.44000,1,25,16777215,1443596580,0,8c24eb89,1240716999">vs：吓尿了</d><d p="1513.46000,1,25,16777215,1443596615,0,2c094f82,1240767879">发大财了</d><d p="525.07600,1,25,16777215,1443596623,0,616bf25a,1240780741">对面4大哥阵容</d><d p="164.72100,1,25,16777215,1443600249,0,b4d08ed0,1240842917">因为你都很差 总结一个字就是菜</d><d p="1003.97000,1,25,16777215,1443600264,0,b4d08ed0,1240865415">菜</d><d p="1934.19000,1,25,16777215,1443600282,0,b4d08ed0,1240896519">太水了</d><d p="1415.54000,1,25,16777215,1443603958,0,3ca2d578,1241048511">你狗0.0</d><d p="777.56300,1,25,16777215,1443607567,0,cdf3c83f,1241069733">牛哥6</d><d p="1677.39000,1,25,16777215,1443607584,0,cdf3c83f,1241109851">撒神附体</d><d p="2268.44000,1,25,16777215,1443607592,0,d996831a,1241128359">有小小直接基地啊</d><d p="1424.22000,1,25,16777215,1443607598,0,a3637b0a,1241143425">09视频里有过这个小黑</d><d p="357.06300,1,25,16777215,1443607600,0,b0f7dd43,1241148671">萌萌真菜 为啥不打do2</d><d p="253.28500,1,25,16777215,1443611234,0,5a6557f2,1241241657">要先画个圈再打</d><d p="501.23000,1,25,16777215,1443611239,0,5a6557f2,1241253219">2333</d><d p="769.81700,1,25,16777215,1443611243,0,5a6557f2,1241265897">23333</d><d p="940.99100,1,25,16777215,1443611256,0,92aa672d,1241305119">动都动不来</d><d p="884.99000,1,25,16777215,1443611271,0,6d4b1b0b,1241348507">这combo看着真爽</d><d p="1011.97000,1,25,16777215,1443611273,0,6d4b1b0b,1241355215">我不管，萌萌你就是菜</d><d p="1681.03000,1,25,16777215,1443614884,0,6d4b1b0b,1241389159">说菜的感觉如何</d><d p="1693.21000,1,25,16777215,1443614885,0,6d4b1b0b,1241390563">不要再玩这个梗了好烦呐2333</d><d p="2308.65000,1,25,16777215,1443614916,0,121a696b,1241489509">我要是小黑就窝在2塔树林里，等他们露头买TP走</d><d p="1683.92000,1,25,16777215,1443614923,0,523760e3,1241512725">菜</d><d p="1256.78000,1,25,16777215,1443618578,0,24d1559d,1241690491">萌萌回家了？</d><d p="1509.39000,1,25,16777215,1443618581,0,24d1559d,1241703209">这波团可以</d><d p="1626.73000,1,25,16777215,1443618583,0,24d1559d,1241709625">手太！</d><d p="1681.90000,1,25,16777215,1443618584,0,24d1559d,1241712783">玩得6</d><d p="2003.60000,1,25,16777215,1443618590,0,24d1559d,1241730253">菜得你发疯</d><d p="704.59600,1,25,16777215,1443622221,0,2e349adf,1241825485">虚空：我猜到你要给我波了，老波顿的意识</d><d p="998.06100,1,25,16777215,1443622227,0,2e349adf,1241839053">意识还有，不过这个操作。。。。。</d><d p="1503.72000,1,25,16777215,1443622238,0,2e349adf,1241872695">一波1600</d><d p="1078.04000,1,25,16777215,1443622252,0,a7cf36ab,1241911705">sf都没婚了</d><d p="74.96800,1,25,16777215,1443622253,0,41a510de,1241916867">的确出手不好啊</d><d p="1483.07000,1,25,16777215,1443622253,0,a7cf36ab,1241917007">这sf真是惨</d><d p="110.08500,1,25,16777215,1443622254,0,41a510de,1241918633">注意补刀啊</d><d p="479.91800,1,25,16777215,1443625860,0,41a510de,1241936773">差点害死牛少</d><d p="566.24500,1,25,16777215,1443625862,0,41a510de,1241941035">瘦不下去的人哭了</d><d p="755.43500,1,25,16777215,1443625865,0,41a510de,1241951393">牛少手速不错</d><d p="25.45900,1,25,16777215,1443629524,0,2f600315,1242109193">马格纳斯之皮</d><d p="1013.44000,1,25,16777215,1443629536,0,82d08ed1,1242133239">萌萌好菜好菜</d><d p="1874.25000,1,25,16777215,1443629536,0,41a510de,1242133825">牛少好文采</d><d p="1219.36000,1,25,16777215,1443629540,0,82d08ed1,1242140213">若风</d><d p="1680.65000,1,25,15138834,1443629541,0,6412fb4a,1242143023">这个回头拱加推推不错啊</d><d p="1695.64000,1,25,16777215,1443629548,0,82d08ed1,1242156097">菜萌萌</d><d p="841.15600,1,25,16777215,1443629556,0,657c77f4,1242170437">可以一下子飞出几十米</d><d p="1677.99000,1,25,16777215,1443629567,0,657c77f4,1242190371">封印班呢</d><d p="1012.47000,1,25,16777215,1443665430,0,cd82cce2,1242656715">跳波啊，老波登</d><d p="926.71000,1,25,16777215,1443665435,0,1d302cad,1242668689">对面阵容也太垃圾了</d><d p="189.69100,1,25,16777215,1443665440,0,1eed18c2,1242679651">看一眼上路嘛</d><d p="1282.27000,1,25,16777215,1443669061,0,1eed18c2,1242727293">6楼靠马路的表示吵死了</d><d p="23.70200,1,25,16777215,1443669070,0,79ef45fb,1242747937">原画拯救世界</d><d p="102.85700,1,25,16777215,1443669072,0,79ef45fb,1242751101">就是菜 不由分说</d><d p="162.89600,1,25,16777215,1443669073,0,79ef45fb,1242753703">就是菜 菜菜菜菜</d><d p="944.99700,1,25,16777215,1443669086,0,79ef45fb,1242786189">vs再来一把跳+A</d><d p="1231.37000,1,25,16777215,1443669092,0,79ef45fb,1242798829">唉哟 这个e加的精髓啊</d><d p="1388.03000,1,25,16777215,1443669095,0,79ef45fb,1242805079">说明这个回复有毒</d><d p="1517.70000,1,25,16777215,1443669097,0,79ef45fb,1242811431">对面上头了</d><d p="1684.03000,1,25,16777215,1443669100,0,79ef45fb,1242818751">三进三出</d><d p="1873.97000,1,25,16777215,1443669105,0,79ef45fb,1242828461">好押韵</d><d p="997.86700,1,25,16777215,1443669117,0,2cda398,1242858687">萌萌真菜233333333</d><d p="5.36500,1,25,16777215,1443669119,0,76866a44,1242863197">来了来了</d><d p="1155.59000,1,25,16777215,1443672720,0,2cda398,1242865475">没有我接不了的团（锅）</d><d p="2422.76000,1,25,16777215,1443672742,0,2cda398,1242916871">再往前一点小黑也要死</d><d p="137.12000,1,25,16777215,1443672743,0,4856ed3,1242919901">萌萌还健身啊！</d><d p="571.76000,1,25,16777215,1443672752,0,4856ed3,1242941147">……</d><d p="223.37100,1,25,16777215,1443675675,0,900d7b8a,1243052507">游走赏金 就指望人头了   估计全程正补不超过20</d><d p="1071.50000,1,25,16777215,1443675697,0,900d7b8a,1243108185">这SF是逗吧  X炮收了人头 就走啊   还想着开大留人</d><d p="1288.29000,1,25,16777215,1443675703,0,900d7b8a,1243125605"> 地方不一样  我这10几线的小城  外面就是一片田  晚上听虫叫 睡的很好</d><d p="1478.06000,1,25,16777215,1443697671,0,68129b6d,1244117575">这影魔好像就没放出过大</d><d p="2425.64000,1,25,16777215,1443701287,0,68129b6d,1244168063">好大的沉默</d><d p="2112.30000,1,25,16777215,1443701306,0,a2144e8a,1244233987">A杖小小+猛犸+VS那攻击美如画啊</d><d p="11.79500,1,25,16777215,1443712297,0,df43ccf6,1244854975">开场谐</d><d p="162.21400,1,25,16777215,1443712299,0,df43ccf6,1244862473">哪里都菜 Y(^_^)Y</d><d p="167.97900,1,25,16777215,1443712305,0,b3fe6b70,1244876381">就是菜 2333</d><d p="2399.02000,1,25,16777215,1443715947,0,df43ccf6,1244970687">一个好大！ （谐）</d><d p="28.50300,1,25,16777215,1443715948,0,4d5da353,1244974177">漏气主播笑出声了</d><d p="997.79100,1,25,16777215,1443715956,0,b3fe6b70,1244988559">那个大不该交</d><d p="1744.54000,1,25,16777215,1443715978,0,4d5da353,1245026215">只能腐蚀你的肉体？</d><d p="1233.04000,1,25,16777215,1443715978,0,b3fe6b70,1245026675">哪里死了</d><d p="1753.00000,1,25,16777215,1443718868,0,b3fe6b70,1245041149">23333</d><d p="2281.59000,1,25,16777215,1443718877,0,b3fe6b70,1245053457">为什么布基地</d><d p="1353.95000,1,25,16777215,1443744510,0,e99d1545,1245277175">刷什么快了？</d><d p="1679.09000,1,25,16777215,1443751829,0,ec2fdea6,1245474763">哈哈</d><d p="937.19200,1,25,16777215,1443751832,0,f9c6a6a7,1245480805">一连什么鬼？  那还叫连么</d><d p="151.51600,1,25,16777215,1443759126,0,bb270fdc,1245700679">健完身一直听的接完生</d><d p="502.93300,1,25,16777215,1443759132,0,bb270fdc,1245715335">自己立FLAG</d><d p="534.18800,1,25,16777215,1443759132,0,bb270fdc,1245716685">又黑DC老师</d><d p="1008.07000,1,25,16777215,1443759140,0,bb270fdc,1245736887">菜</d><d p="1133.98000,1,25,16777215,1443759142,0,bb270fdc,1245742209">让你不看路</d><d p="1705.50000,1,25,16777215,1443759152,0,bb270fdc,1245767451">我赵日天不服</d><d p="628.26500,1,25,16777215,1443762082,0,390213b6,1245913503">虚空ID, 总有刁民想害朕</d><d p="921.23600,1,25,16777215,1443762087,0,390213b6,1245927957">直接把SF控到哭瞎</d><d p="1721.46000,1,25,16777215,1443762094,0,a982aaef,1245947281">鸟：给你个树枝慢慢撸</d><d p="97.29800,1,25,16777215,1443784073,0,ecd4857e,1247093047">补刀美如画</d><d p="502.45500,1,25,16777215,1443784077,0,3114177c,1247108089">医生。我还可以救活！</d><d p="1152.07000,1,25,16777215,1443787731,0,ecd4857e,1247304985">    菜！菜~~~~</d><d p="1849.02000,1,25,16777215,1443791346,0,ecd4857e,1247357937">又可以刷菜了~</d><d p="2229.09000,1,25,16777215,1443791363,0,7c15101a,1247421399">作曲家！</d><d p="94.61200,1,25,16777215,1443791380,0,b38ec0fa,1247484881">菜鸡萌萌</d><d p="172.45500,1,25,16777215,1443791382,0,b38ec0fa,1247489783">我不听，就是菜233</d><d p="707.51400,1,25,16777215,1443802359,0,271fcbee,1248029005">虚空 这条的 </d><d p="587.30100,1,25,16777215,1443834563,0,fc0462fa,1248487849">每天吃夜宵的表示60都上不去</d><d p="701.91500,1,25,16777215,1443834565,0,fc0462fa,1248491923">虚空吓尿了</d><d p="1236.32000,1,25,16777215,1443834574,0,fc0462fa,1248510935">老年选手の日常幻觉</d><d p="1730.29000,1,25,16777215,1443834582,0,fc0462fa,1248529411">求树枝的心理阴影面积</d><d p="1682.24000,1,25,16777215,1443848502,0,da29370,1249248177">封印班又阵亡！？</d><d p="365.44000,1,25,16777215,1443863125,0,2e00f2ba,1249992335">因为菜2333333</d><d p="1796.24000,1,25,16777215,1443870473,0,46a43f92,1250459971">这波我好强2333</d><d p="778.78300,1,25,16777215,1443874090,0,50501a4f,1250522275">2333</d><d p="358.00500,1,25,16777215,1443888734,0,af4d9376,1251403947">英语十级</d><d p="2076.89900,1,25,16777215,1443895333,0,f5d879aa,1251628607">拱了个虚空</d><d p="949.22100,1,25,16777215,1443902646,0,e9f625dc,1251709627">已经GG了</d><d p="1007.09000,1,25,16777215,1443924643,0,a9f8b95c,1252088683">菜23333</d><d p="923.49300,1,25,16777215,1443938570,0,adae3607,1252872177">110吗？场面控制不住了。。</d><d p="1638.00000,1,25,16777215,1443942182,0,adae3607,1252912945">4个..</d><d p="1246.94000,1,25,16777215,1443960527,0,b6de3b9d,1254075253">两楼水平</d><d p="2271.48000,1,25,16777215,1444003728,0,8916c18c,1255260019">bgm是什么鬼，一开始还以为是李白</d><d p="1296.96000,1,25,16777215,1444032266,0,832b9e72,1256492739">不。。买房不能买靠着街的不是吗。。和楼层无关啊</d><d p="232.39000,1,25,16777215,1444043263,0,93fc67fc,1257185083">游走不容易啊</d><d p="1864.00000,1,25,16777215,1444054213,0,b5653587,1257805623">毕竟不是史诗猛犸</d><d p="1672.81000,1,25,16707842,1444057900,0,5e00f0fb,1258109657">卧槽6666666</d><d p="654.45800,1,25,16777215,1444122312,0,b5c19146,1260312507">@伍声2009</d><d p="1085.80000,1,25,16777215,1444194110,0,4c7b71fc,1263326433">E给小小啊，多厉害</d><d p="1699.89000,1,25,16777215,1444197720,0,4c7b71fc,1263371661">蓝不够2套</d><d p="643.06500,1,25,16777215,1444313428,0,2c003b39,1266740833">一眼下去，以为是09的旧id，，，</d><d p="658.98100,1,25,16777215,1444313429,0,2c003b39,1266741421">@2009</d><d p="90.40600,1,25,16777215,1444396160,0,9b886cce,1268306757">233</d><d p="790.53200,1,25,16777215,1444882368,0,3283bff7,1279076387">真的够菜的</d><d p="1141.60000,1,25,16777215,1444899902,0,2f7633d5,1279395557">菜</d><d p="223.05200,1,25,16777215,1445151782,0,3d9b9a7f,1286879969">人家赏金是想让你少吃一下塔的伤害啊233</d><d p="499.73600,1,25,16777215,1445151787,0,3d9b9a7f,1286894517">刚刚vs锤了不回头还有戏</d><d p="571.33700,1,25,16777215,1445151789,0,3d9b9a7f,1286899169">休息做的不好，长肉要睡得好</d><d p="995.84200,1,25,16777215,1445151796,0,3d9b9a7f,1286920379">不吹不黑确实娱</d><d p="1053.90000,1,25,16777215,1445151797,0,3d9b9a7f,1286923747">绝佳配合233</d><d p="1146.25000,1,25,16777215,1445151799,0,3d9b9a7f,1286928575">其实就是菜</d><d p="961.32900,1,25,16777215,1446113182,0,44db3232,1310809435">-2</d><d p="2291.01000,1,25,16777215,1446113206,0,44db3232,1310858235">小小带着躺赢</d><d p="938.09400,1,25,16777215,1448899939,0,e51beee9,1386844867">VS可以锤吼换啊（斜眼</d><d p="1301.62000,1,25,16777215,1453986588,0,27312d68,1528691269">我房子在山脚下,非常安静凉爽</d><d p="2365.06000,1,25,16777215,1453990206,0,27312d68,1528763945">授予狂战斧</d><d p="1667.00000,1,25,16777215,1455433390,0,82741e21,1593818517">不是能波死吗</d><d p="1256.71000,1,25,16777215,1456128270,0,7f1a571d,1627480107">两楼水平！</d><d p="1706.07000,1,25,16777215,1456312029,0,2038b183,1633943703">波的话自己就死了</d><d p="362.32300,1,25,16777215,1456312043,0,e82d666,1633984671">以前立得毒誓 当初打得不爽开小号喷DOTA2 结果被人发现233</d><d p="1363.33000,1,25,16777215,1456312061,0,e82d666,1634036697">一根短棍就敢说蝴蝶好了 现在1700只是说刷新快了已经很好了</d><d p="518.97600,1,25,16777215,1466647815,0,22bcffe1,1987624289">锤一下你自己回头的啊</d><d p="859.89400,1,25,16777215,1469595678,0,22bcffe1,2155193601">结果还是牛头自己点的</d><d p="1221.28000,1,25,16777215,1469595684,0,22bcffe1,2155230451">拉兵</d><d p="1687.66000,1,25,16777215,1469595694,0,22bcffe1,2155295369">然而还是菜</d><d p="1289.62000,1,25,16777215,1469617642,0,250b7b1,2157209011">看习惯09随时随地ks，感觉好甜</d><d p="87.97700,1,25,16777215,1474463347,0,669b7d53,2430414137">刁民想害朕</d><d p="997.46700,1,25,16777215,1477465428,0,2c069f87,2597630501">刚跳一下波一下推不就好了</d><d p="923.74400,1,25,16777215,1483456270,0,1cd5660,2811236627">sf摇大摇到一半23333333</d><d p="959.53100,1,25,16777215,1483456270,0,1cd5660,2811239615">-2</d><d p="1009.83000,1,25,16777215,1483456272,0,1cd5660,2811244179">没有你扣不了的脚</d><d p="1988.39000,1,25,16777215,1483456290,0,1cd5660,2811310503">仁义无双总司令</d></i>