<?xml version="1.0" encoding="UTF-8"?><i><chatserver>chat.bilibili.com</chatserver><chatid>6542776</chatid><mission>0</mission><maxlimit>3000</maxlimit><state>0</state><real_name>0</real_name><source>e-r</source><d p="21.52500,1,25,16777215,1457528993,0,1ff86706,1670028607">第一，感谢制药组!!!</d><d p="326.31400,1,25,16777215,1457528999,0,1ff86706,1670045301">wwwww</d><d p="348.02200,1,25,16777215,1457528999,0,1ff86706,1670046165">wwwwwwwwww</d><d p="49.17000,1,25,16777215,1457532612,0,68e26da2,1670080729">在路上遇到此人请躲避</d><d p="34.32600,1,25,16777215,1457532621,0,2529ee88,1670105927">好羞耻</d><d p="76.57200,1,25,16777215,1457532622,0,2529ee88,1670108183">一直在想摄影师会不会笑场</d><d p="33.63500,1,25,16777215,1457532624,0,edad3b02,1670114453">求路人心里的阴影面积</d><d p="346.41900,5,25,16711680,1457536268,0,edad3b02,1670236803">一 脸 懵 逼</d><d p="1132.99000,1,25,16777215,1457536288,0,edad3b02,1670286215">好羞耻</d><d p="120.43000,1,25,16777215,1457539973,0,152cda0d,1670438347">观众们，有人想娶她的吗？？</d><d p="717.01200,1,25,16777215,1457550196,0,89e8e344,1670634789">就是他令鍊金術士系列畫風變萌?</d><d p="829.58500,1,25,16777215,1457550198,0,89e8e344,1670635597">現在的設計看慣了比較萌</d><d p="1074.26000,1,25,16777215,1457550202,0,89e8e344,1670637137">BD封面的溝....</d><d p="826.37500,1,25,16777215,1457564872,0,d4b5f1f7,1670713315">左(hidari)</d><d p="136.73700,1,25,16777215,1457583124,0,a3139d9e,1670909009">23333333333三倍速梨衣熊</d><d p="138.67600,1,25,16777215,1457600702,0,1f6382de,1671677119">wwwwwwwww</d><d p="132.07700,1,25,16777215,1457600713,0,f24913ce,1671695241">快轉好評233333333</d><d p="0.67200,1,25,16777215,1457600747,0,2cdd61d8,1671750485">熊熊</d><d p="312.97200,1,25,16777215,1457600749,0,f24913ce,1671753655">不是幫忙打掃嗎w</d><d p="20.99800,1,25,16777215,1457604386,0,92f804b,1671821009">梨衣熊啊，在街上咱收敛点儿呗</d><d p="213.35300,1,25,16777215,1457604395,0,92f804b,1671839551">这里一跳一挑的，可爱死了</d><d p="1569.63000,1,25,16777215,1457608077,0,9096ccdd,1672050169">導演桑一直偷笑XD</d><d p="226.64100,1,25,16777215,1457622661,0,32778ec0,1672540481">好平</d><d p="43.20400,1,25,16711680,1457676158,0,218d393c,1673421435">熊出没 路人火速逃离</d><d p="1132.27000,1,25,16777215,1457698131,0,4ba7c962,1674247761">制作人没跟上熊的思维23333</d><d p="1206.68000,1,25,16777215,1457698134,0,4ba7c962,1674257591">茫然的印象或者概念吧…</d><d p="954.85500,1,25,16777215,1457788167,0,91760c3e,1677382067">完全不像好不好www</d><d p="441.04200,1,25,16777215,1458284633,0,3ebab3ad,1689363479">好多东西</d><d p="1551.04000,1,25,16777215,1458288265,0,3ebab3ad,1689410825">...笑得停不下来</d><d p="20.18900,1,25,16777215,1458310220,0,2c54101a,1690383639">画风完全不对的人。。。</d><d p="125.73500,1,25,16777215,1466176299,0,b239dca3,1968846261">有 熊熊我抱回家咯</d><d p="360.58400,1,25,16777215,1466946566,0,aef5f5a2,2002078423">笑死了</d><d p="1132.18000,1,25,16777215,1468303322,0,32486d29,2074207857">wwwwww</d><d p="303.54700,1,25,16777215,1481882794,0,b239dca3,2753393169">迷之BGM</d></i>