<?xml version="1.0" encoding="UTF-8"?><i><chatserver>chat.bilibili.com</chatserver><chatid>6543211</chatid><mission>0</mission><maxlimit>1000</maxlimit><state>0</state><real_name>0</real_name><source>e-r</source><d p="174.56700,1,25,16777215,1457532621,0,b57a6bef,1670104553">这个职业感觉好渣啊！</d><d p="228.02900,1,25,16777215,1457536291,0,36a77a45,1670292813">这伤害00  尿了</d><d p="236.44800,1,25,41194,1457536296,0,ebe2430a,1670303389">点穴枪威力不错啊</d><d p="197.60100,1,25,16777215,1457539942,0,78ef1e6d,1670394867">看看连招流畅不 看来还行 可以连一个</d><d p="184.99100,1,25,16777215,1457568489,0,353f59ab,1670719761">装备cc</d><d p="199.38700,1,25,16777215,1457568490,0,353f59ab,1670720055">而且不知道多少级的。武器灵越左右槽没有</d><d p="218.02100,1,25,16777215,1457583151,0,fe109908,1670954863">伤害没打出来</d><d p="237.54200,1,25,16777215,1457619034,0,ec20a5a0,1672466769">这职业没控么...?</d><d p="224.03000,1,25,16777215,1457802061,0,c0802114,1678022299">好弱鸡的职业。。</d><d p="208.12000,1,25,16777215,1457874555,0,7284269e,1680444555">前面的连装备情况都不清楚 就知道职业渣了？ </d><d p="244.11000,1,25,16777215,1457874556,0,7284269e,1680447473">有控的 up没用而已</d><d p="182.93400,1,25,16777215,1457878208,0,c74c539f,1680609041">前面的，你也不看看面板，都假紫←_←</d><d p="236.98300,1,25,16777215,1457878209,0,c74c539f,1680614527">看装备啊，游戏下了没?</d><d p="260.09100,1,25,16777215,1457878210,0,c74c539f,1680616005">控不错</d><d p="244.40500,1,25,16777215,1457892160,0,320c80e0,1681113009">有控制，一觉，2觉和80还有雷枪都是控制，up一个都没用出来··</d><d p="210.83600,1,25,16777215,1458122787,0,474c5930,1685723257">很明显新号啊，刚刚获得那个成就是背击还是什么是非常前期的成就</d><d p="223.42000,1,25,16777215,1458141060,0,12f090b7,1686349511">二觉只有枪尾打中了。。。悲哀。。。幸运E阿</d><d p="71.28300,1,25,16777215,1458712939,0,dd6656,1701378129">延迟高的特效的没了</d><d p="178.85000,1,25,16777215,1458712943,0,dd6656,1701383659">←看装备了吗？延迟又这么大那个职业能厉害？</d><d p="309.54500,1,25,16777215,1458712946,0,dd6656,1701386717">看的都累</d><d p="226.98800,1,25,16777215,1458712948,0,dd6656,1701389039">枪兵本来就不适合打这里</d><d p="89.12400,1,25,16777215,1458716582,0,ecf1931f,1701431621">有替身攻击？</d><d p="273.45100,1,25,16777215,1458983157,0,1cc021cf,1708210125">旋转蓄力和雷枪呢？</d><d p="35.87200,1,25,16777215,1459332367,0,89b90c44,1717467899">bgm???????</d><d p="184.88400,1,25,16777215,1459642095,0,2750f348,1726605269">这伤害笑尿了</d><d p="214.66900,1,25,16777215,1459642096,0,2750f348,1726606125">两个觉醒都空了，服了</d><d p="300.55300,1,25,16777215,1459642098,0,2750f348,1726608321">这后撤步有点意思</d><d p="186.68300,1,25,16777215,1459681641,0,18523d6,1728744761">左右槽都没开请别吐槽伤害</d><d p="197.49500,1,25,16777215,1460034569,0,42aae21c,1739607489">应该是直接到85的升级卷升的</d><d p="302.93100,5,25,16711935,1460106323,0,8050a80a,1741372677">恭喜爆出；80级假紫转圣物使用说明书</d><d p="215.10300,1,25,16777215,1461564129,0,ffd42a2c,1790469713">一身假紫 属性肯定不咋地 左右槽都没开</d><d p="133.89900,1,25,16777215,1463864717,0,1a022692,1871988357">又是一个吃武器的职业 Y轴攻击范围好小</d><d p="109.86300,1,25,16777215,1463864750,0,ffd42a2c,1872001649">有后撤攻击 居然不用 完全可以脱手放其他的技能</d><d p="199.92700,1,25,16777215,1463864753,0,ffd42a2c,1872002599">去腾讯看 体验服的视频 那才比较合理</d><d p="260.17000,1,25,16777215,1465196638,0,39eee651,1929341101">以后会不会出个双枪啊</d><d p="166.51700,1,25,16777215,1466082566,0,a42ceada,1964761841">说实在的 爆发是真高</d><d p="73.52200,1,25,16777215,1466355685,0,5446b182,1977167771">伤害感人</d><d p="148.18100,1,25,16777215,1475853108,0,881b41ce,2519446017">可以肯定，刷图不如征战</d><d p="59.42700,1,25,16777215,1477573761,0,ddf46d81,2602231141">DNF的音乐是真的不错</d></i>