<?xml version="1.0" encoding="UTF-8"?><i><chatserver>chat.bilibili.com</chatserver><chatid>6543993</chatid><mission>0</mission><maxlimit>500</maxlimit><state>0</state><real_name>0</real_name><source>e-r</source><d p="9.19000,1,25,16777215,1457536285,0,11f9071e,1670279109">没有人么!</d><d p="10.72800,4,25,16777215,1457539978,0,c95240c4,1670444487">谢谢上面这位第一个给我弹幕的~~up主我本人有点激动~~</d><d p="11.74200,1,25,16777215,1457583153,0,4be0e5cd,1670959843">看到dk表示支持~~~</d><d p="93.07700,1,25,16777215,1457583154,0,4be0e5cd,1670962691">歌词好直白。。。哈哈哈哈</d><d p="28.49600,1,25,16777215,1457597062,0,41d42c0b,1671622643">从土豆看到up主的，来b站看看有没有结果真有太棒了</d><d p="49.60400,1,25,16777215,1457597062,0,41d42c0b,1671623137">我要做成mp3单曲循环啦啦啦~</d><d p="76.64200,1,25,16777215,1457597063,0,41d42c0b,1671623709">好好听dk的声音&gt;_&lt;</d><d p="119.29600,1,25,16777215,1457597064,0,41d42c0b,1671624575">好喜欢这嘶喊</d><d p="26.73800,1,25,16777215,1457611718,0,d3261a02,1672154713">Dk唱歌 好久没听了</d><d p="41.73600,1,25,16777215,1457622669,0,ae69225e,1672561631">这首歌好听，可惜没有发行，特别喜欢嘶吼那</d><d p="13.70800,1,25,16777215,1457788149,0,ab794df3,1677310931">这首歌好好听</d><d p="53.75700,1,25,16777215,1457863590,0,41d42c0b,1679961977">声音苏死了</d><d p="16.16700,1,25,16777215,1457931669,0,2b7729ff,1681528953">来看Dicky导师</d><d p="62.16700,1,25,16777215,1459166911,0,fa443072,1713816945">好久没听dicky唱歌了，求发行阿</d><d p="64.27300,1,25,16777215,1459166911,0,fa443072,1713817737">花痴的我</d><d p="39.71200,1,25,16777215,1459328754,0,b3787145,1717442653">最爱张卫健</d><d p="101.54400,1,25,16777215,1462078911,0,7487aeb8,1807894733">娇俏跺脚~</d><d p="69.40900,1,25,16777215,1462335160,0,8bd293b3,1818221213">好好听</d><d p="71.97700,1,25,16777215,1462335161,0,8bd293b3,1818222083">最爱DK</d><d p="77.46100,1,25,16777215,1464429981,0,7c521a63,1897993495">谁做的曲</d><d p="48.02500,1,25,16777215,1467014696,0,274684b7,2004855059">dk好棒ヾ ^_^♪</d><d p="74.73000,1,25,16777215,1467014696,0,274684b7,2004856511">(*'▽'*)♪</d><d p="21.91900,1,25,16777215,1472915470,0,f14678b2,2371633667">来看dk</d><d p="13.40300,1,25,16777215,1473958860,0,e32da916,2411181575">在贴吧看到的</d><d p="68.64700,1,25,16777215,1474254700,0,fa392d25,2423958473">能唱能说能演</d><d p="44.17600,1,25,16777215,1480424964,0,443d9dab,2705157659">表白up</d><d p="90.98800,1,25,16777215,1489075920,0,8692f1fa,3084484098">合音声太大了</d><d p="75.24600,1,25,0,1491736052,0,733873e3,3205529148">我是最近才掉dk坑里的。。。</d><d p="41.21000,1,25,16777215,1493802300,0,5066dec0,3306162392">好苏好苏</d><d p="119.29500,1,25,16777215,1498576313,0,230b9f82,3498036878">发际线好明显哦dk</d><d p="121.60100,1,25,16777215,1500908870,0,bd4a4b0,3600595971">普通话比原来好多了</d><d p="22.95300,1,25,16777215,1502782872,0,b89c109d,3699759674">dkdkdkdk</d><d p="31.97100,1,25,16777215,1512482952,0,b72656,4015782005">唱得好好听</d><d p="68.61400,1,25,16777215,1512640779,0,bf1bcd85,4019283284">好喜欢DK</d><d p="21.36200,1,25,16777215,1512744328,0,b72656,4022123377">正能量满满的DK</d><d p="104.67500,1,25,16777215,1512744425,0,b72656,4022128483">娇俏等等我</d><d p="32.41800,1,25,16777215,1513000571,0,b72656,4029930605">声音好听死了啦</d><d p="27.77100,1,25,16777215,1513173258,0,b72656,4033665671">香港撩台湾萌大陆正，多面的DK</d><d p="120.56100,1,25,16777215,1518576957,0,771d7466,4297169215">嘶吼好好听</d><d p="61.63500,1,25,16777215,1542014943,0,4d0fb69a,7797614083833856">这应该不是黄国伦写的吧，跟以前的不一样，不过这个好听</d></i>