<?xml version="1.0" encoding="UTF-8"?><i><chatserver>chat.bilibili.com</chatserver><chatid>6544130</chatid><mission>0</mission><maxlimit>1000</maxlimit><state>0</state><real_name>0</real_name><source>k-v</source><d p="212.37300,1,25,16777215,1457586067,0,f72eb3c4,1671034093">感觉调好低</d><d p="16.72400,1,25,16777215,1457690811,0,dd199cec,1673881995">大声地告诉我我第几？</d><d p="22.66100,1,25,16777215,1465088988,0,b914c805,1924718173">first</d><d p="131.68500,1,25,16777215,1465092621,0,fd967d24,1924799789">化不去千千心结</d><d p="39.44800,1,25,16777215,1465092628,0,dcd3b974,1924816501">聪聪北鼻</d><d p="92.16800,1,25,16777215,1465099938,0,a5c39d5c,1925169451">表白聪聪(´ε｀ )♡</d><d p="63.74300,1,25,14811775,1465164416,0,ca2024d6,1928220153">好听</d><d p="87.46700,1,25,16777215,1465179010,0,72970cb7,1928445585">伴奏有点响</d><d p="118.11600,1,25,16777215,1465657910,0,fa94f92,1950534821">好好听(≧▽≦)表白阿婆主(/≧▽≦/)</d><d p="58.46400,1,25,16777215,1467727814,0,b6ceb073,2041897663">这里好萌好喜欢这个感觉qwq</d><d p="27.02700,1,25,16777215,1471496483,0,eb0538b3,2285947585">啊好好听！好棒！</d><d p="223.09600,1,25,16777215,1471496488,0,eb0538b3,2285975177">这里超好听！</d><d p="1.78800,1,25,41194,1471522086,0,be50899,2288481071">第一！</d><d p="18.67100,1,25,16777215,1471522092,0,4b781ea3,2288517091">美的</d><d p="48.50400,1,25,16777215,1471522093,0,4b781ea3,2288520093">受音哎，好暖</d><d p="6.28100,1,25,16777215,1471623179,0,6177ecbf,2296166401">好像夏达的作品</d><d p="54.12500,1,25,16777215,1471633388,0,ef6864c9,2296477183">好了粉了</d><d p="66.29200,1,25,16777215,1471633389,0,ef6864c9,2296477557">给勾搭嘛</d><d p="141.33900,1,25,16777215,1471659011,0,7ff8d40c,2297082519">偷偷承包</d><d p="23.46100,1,25,16777215,1471669285,0,fe879805,2298017617">好听</d><d p="20.06100,1,25,16777215,1471694882,0,56841185,2300145331">萌萌哒哎s</d><d p="80.82000,1,25,16777215,1471709528,0,8f20b30,2301643951">前面的+1</d><d p="0.48500,5,25,14811775,1471709546,0,38ebe9ff,2301729423">我先表白⊙▽⊙!</d><d p="32.85300,1,25,16777215,1471709549,0,67374629,2301744679">表白~</d><d p="36.53900,1,25,16777215,1471712484,0,e1e824b9,2301954389">好棒！</d><d p="24.14200,1,25,16777215,1471716142,0,4b3472f9,2302099933">大声告诉我。我第几</d><d p="149.77000,5,25,15138834,1471719837,0,2cbb070d,2302235877">表白并且承包！说休想都是后来的！</d><d p="54.84300,1,25,15138834,1471734424,0,a2cbd41c,2302368289">好听！ 受音棒棒哒( • ̀ω•́ )✧</d><d p="30.12400,1,25,16777215,1471741750,0,23694014,2302586815">极乐净土过来的带我</d><d p="65.09100,1,25,16777215,1471741750,0,23694014,2302588411">快快，我要把你打包回家</d><d p="4.38600,1,25,16777215,1471749111,0,5c90b819,2303208449">极乐净土滚来的</d><d p="87.02700,1,25,16707842,1471752772,0,2ab9adaa,2303505007">前面+1</d><d p="174.52000,1,25,16707842,1471752774,0,2ab9adaa,2303516377">好好听(^・ω・^ )好流畅( ¯ᒡ̱¯ )و</d><d p="36.49600,1,25,16777215,1471755678,0,72198d95,2303642079">极乐净土过来的不能算我不能算我……</d><d p="87.45900,1,25,16777215,1471755678,0,72198d95,2303646749">投币失败几个意思！</d><d p="99.18300,1,25,16777215,1471755678,0,72198d95,2303647857">我要生气了！哼唧╭(╯^╰)╮</d><d p="73.27100,1,25,16777215,1471759349,0,d99b3493,2304023131">休想</d><d p="43.78800,1,25,16777215,1471759379,0,7a689ada,2304176723">+1</d><d p="7.34100,1,25,16777215,1471798871,0,a2ff28b2,2307396125">极乐净土来的带我一个！</d><d p="25.88000,1,25,16777215,1477228148,0,613c2ca3,2586088857">_(:зゝ∠)_</d><d p="78.62500,1,25,16777215,1478992041,0,86d45530,2656856649">男神</d><d p="42.30800,1,25,16777215,1479215395,0,a2fea3fd,2664668657">迎新晚会来的</d><d p="18.00000,1,25,16777215,1481101518,0,72222143,2727199433">极乐净土+1</d><d p="13.58200,1,25,16777215,1481213542,0,ef8407f1,2731268033">我也极乐净土!</d><d p="17.47600,1,25,0,1484359825,0,f4cb8e38,2844775585">极乐净土的等等我</d><d p="10.91000,1,25,16777215,1498266556,0,3fabc894,3485832939">女装滚来的</d><d p="41.35300,1,25,16777215,1498273904,0,dcd55187,3486184700">极乐净土过来的等我</d><d p="77.39100,1,25,16777215,1498277533,0,54a7f5ba,3486266260">伴奏声突出了</d><d p="56.39000,1,25,0,1498284139,0,8aaa9a10,3486665820">妖尾来的</d><d p="16.28700,1,25,16777215,1498291494,0,f066b00a,3487115100">女装+1</d><d p="33.42200,1,25,16777215,1498428389,0,f94534dd,3492545870">女装过来别走</d><d p="60.13800,1,25,16777215,1500030427,0,6157f860,3558689970">www果然还是超喜欢羲聪的～www</d><d p="34.87400,1,25,15138834,1501128640,0,d6245f92,3610961761">极乐净土+1</d><d p="70.10400,1,25,16777215,1501661882,0,5da829da,3639389976">桃源恋歌哦不，最炫民族风过来的</d><d p="41.90600,1,25,16777215,1506861998,0,d8dd463c,3850620344">考古考古</d><d p="196.88000,1,25,16777215,1528553166,0,d18b6a1b,739765924659200">我来证明你开了弹幕</d></i>