<?xml version="1.0" encoding="UTF-8"?><i><chatserver>chat.bilibili.com</chatserver><chatid>5390331</chatid><mission>0</mission><maxlimit>1000</maxlimit><state>0</state><real_name>0</real_name><source>e-r</source><d p="110.06900,1,25,16777215,1450346785,0,c2aa2ab4,1423077495">蓝宝石战神卡</d><d p="6.15300,1,25,16777215,1450350426,0,a7c835e4,1423160601">占领第一！</d><d p="35.23800,1,25,16777215,1450350428,0,4be19451,1423164093">！？</d><d p="230.81100,1,25,16777215,1450350442,0,b9b14533,1423194701">hahahah</d><d p="246.89500,1,25,16777215,1450350459,0,4be19451,1423231707">三个逗比，真是好兄弟</d><d p="36.12500,1,25,16777215,1450350463,0,be732fd9,1423240641">这都没事</d><d p="50.05700,1,25,16777215,1450350464,0,be732fd9,1423242131">不信抬头看，苍天饶过谁</d><d p="102.18300,1,25,16777215,1450350465,0,be732fd9,1423244337">漂移甩炮</d><d p="129.54600,1,25,16777215,1450350466,0,be732fd9,1423246293">这xx</d><d p="199.94900,1,25,16777215,1450350467,0,be732fd9,1423249369">让你半自动，没弹了吧</d><d p="249.08200,1,25,16777215,1450350468,0,be732fd9,1423251613">目的也算达到了</d><d p="106.85800,1,25,16777215,1450350479,0,bb69cca6,1423274195">果然是蓝钻贵族</d><d p="38.46400,1,25,16777215,1450354112,0,10ad71fc,1423348945">E25先开炮打死了</d><d p="126.43600,1,25,16777215,1450354115,0,10ad71fc,1423355619">这25T也是蠢货一个偷火炮没蛋还不跑</d><d p="197.60900,1,25,16777215,1450354127,0,10ad71fc,1423383577">这E25有病？</d><d p="3.67300,1,25,16777215,1450357740,0,dc05b6d4,1423414655">曲线行驶好评</d><d p="33.23800,1,25,16777215,1450357741,0,dc05b6d4,1423417503">迷一般的CQC</d><d p="51.17500,1,25,16777215,1450357741,0,dc05b6d4,1423418611">死也要拉个垫背的</d><d p="100.54100,1,25,16777215,1450357742,0,b657f172,1423421727">蓝钻贵族</d><d p="131.05600,1,25,16777215,1450357760,0,f32a04d2,1423467065">这是火炮？</d><d p="228.11800,1,25,16777215,1450357786,0,bb2c0f9c,1423528681">23333</d><d p="72.60000,1,25,16777215,1450357788,0,2724f3ea,1423535523">不好笑别看，没人求你看</d><d p="124.65000,1,25,16777215,1450357789,0,2724f3ea,1423538359">这XX没蛋也来绕啊...</d><d p="188.45000,1,25,16777215,1450357790,0,2724f3ea,1423541143">二人转</d><d p="225.31700,1,25,16777215,1450357791,0,2724f3ea,1423542907">噗</d><d p="53.30200,1,25,16777215,1450357795,0,244baf1d,1423554031">没炮弹了= =</d><d p="125.94500,1,25,16777215,1450361428,0,c8037f10,1423638155">23333</d><d p="231.43500,1,25,16777215,1450361430,0,c8037f10,1423644649">豹原好逗</d><d p="31.21100,1,25,16777215,1450361438,0,36b9c905,1423666769">CQC!</d><d p="81.81100,1,25,16777215,1450361440,0,36b9c905,1423669953">大命犀牛</d><d p="226.87600,1,25,16777215,1450361455,0,731a881c,1423706597">23333</d><d p="70.17700,1,25,16777215,1450365089,0,f82279a9,1423787111">最后一个火炮大家玩一下怎么了？这也能有优越感？</d><d p="227.66000,1,25,16777215,1450365092,0,f82279a9,1423793389">帮倒忙</d><d p="136.66800,1,25,16777215,1450368771,0,dd750d40,1423918709">263TD</d><d p="200.08400,1,25,16777215,1450378982,0,586eccf0,1424003381">←没弹了</d><d p="76.26000,1,25,16777215,1450400992,0,b4a85e93,1424129617">等下犀牛进十级房</d><d p="200.64600,1,25,16777215,1450400994,0,b4a85e93,1424131167">半自动步枪没蛋了</d><d p="135.39600,1,25,16777215,1450414873,0,9c2522f9,1424390837">别理那货，就是个无脑喷的家伙</d><d p="241.56700,1,25,16777215,1450414916,0,d17b431,1424468999">哈哈哈哈哈哈</d><d p="34.60100,5,25,15138834,1450422186,0,3e271341,1424569151">不是CQC.是开炮打死的，掉下去的是个尸体，</d><d p="28.20900,1,25,16777215,1450444145,0,60779bc1,1425365425">帧数好高！！</d><d p="78.28700,1,25,16777215,1450444151,0,60779bc1,1425384389">这俩怎么进来的？</d><d p="72.13300,1,25,16777215,1450455134,0,62f7fc26,1425901905">←这么玩不是挺好玩的么</d><d p="231.29200,1,25,16777215,1450461737,0,c3c2fa6a,1426070551">233333333333</d><d p="95.68300,1,25,16777215,1450487366,0,d03d4aad,1426284701">机智</d><d p="96.03700,1,25,16777215,1450501314,0,524fe912,1426859399">前面说不好笑的脑子有坑？</d><d p="129.05700,1,25,16777215,1450519613,0,2c02a2fc,1427648383">前面偷火炮那个，这是263</d><d p="214.97200,1,25,16777215,1450782434,0,208436c0,1434517911">卡主三个的预感</d><d p="19.92200,1,25,16777215,1450936959,0,ebcd158a,1437905567">踩死</d><d p="105.46500,1,25,16777215,1450936960,0,ebcd158a,1437907825">这漂移？</d><d p="178.84000,1,25,16777215,1450936962,0,ebcd158a,1437910289">绝命绕圈圈</d><d p="187.63800,1,25,16777215,1450940582,0,bdf08040,1437937007">炮塔</d><d p="241.38700,1,25,16777215,1450966257,0,85179a64,1438918133">好和谐</d><d p="66.01700,1,25,16777215,1450976491,0,d9e6d9ba,1439194931">全歼党的荣耀！</d><d p="100.91700,1,25,16777215,1450976492,0,d9e6d9ba,1439195919">蓝名ELC</d><d p="107.66700,1,25,16777215,1450976492,0,d9e6d9ba,1439196319">会漂移的ELC你怕不怕？</d><d p="252.44700,1,25,16777215,1451275963,0,7d34d8b7,1447481653">挖个坑把你们都埋了</d><d p="197.69400,1,25,16777215,1451387252,0,102990a0,1449977763">没炮弹了</d><d p="238.34200,1,25,16777215,1451790662,0,5f66bc7e,1461971135">233333</d><d p="192.38400,1,25,16777215,1452093089,0,2916254e,1470698101">同是无炮塔，何必为难</d><d p="52.45200,1,25,16777215,1452733745,0,2916254e,1486772115">苍天绕过谁</d><d p="230.08500,1,25,16777215,1452733748,0,2916254e,1486774161">漂移甩炮此处可鬼畜</d><d p="70.96500,1,25,16777215,1452769664,0,8e697601,1487868355">多大的仇啊</d><d p="121.91900,1,25,16777215,1452769665,0,8e697601,1487870691">宇宙级的漂移</d><d p="190.93100,1,25,16777215,1453003974,0,c4068a19,1495076185">25没单了</d><d p="65.85100,1,25,16777215,1453133523,0,1f21e6cd,1499656563">杀父之仇</d><d p="240.16300,1,25,16777215,1453306324,0,dc09b03,1504679511">不是故意的吗23333</d><d p="100.25300,1,25,16777215,1453306360,0,cac74a06,1504752457">蓝钻会员</d><d p="111.82500,1,25,16777215,1453496749,0,51b00811,1510570875">sb们关键是伊拉克穿了超潘正面！！还是漂移</d><d p="43.95700,1,25,16777215,1454749541,0,f9e560b1,1561148611">队友莫名躺枪</d><d p="73.80100,1,25,16777215,1455880048,0,633dfda1,1615616121">不看别瞎逼逼影响别人</d><d p="98.61100,1,25,16777215,1455880048,0,633dfda1,1615619895">说不好笑的自己脑子被驴踢了</d><d p="138.28400,1,25,16777215,1455880050,0,633dfda1,1615626973">自己逼裂没事进视频里下逼逼</d><d p="226.65900,1,25,16777215,1457579481,0,5be8c84b,1670860763">2333</d><d p="237.86300,1,25,16777215,1457579481,0,5be8c84b,1670861073">3个噗</d><d p="90.77900,1,25,16777215,1461204630,0,77d38315,1777189845">undertale的音乐！！小羊战斗曲！！！</d><d p="31.87500,1,25,16777215,1461211954,0,77d38315,1777373333">Undertale的音乐！</d><d p="114.15400,1,25,16777215,1461233185,0,84b07163,1778024439">好久不见的图</d><d p="226.52900,1,25,16777215,1461582458,0,7682f281,1791158889">火炮看到了就笑了</d><d p="39.19800,5,25,15138834,1468145170,0,5a5af993,2065091267">扯淡，炮是td开的</d><d p="49.69400,1,25,16777215,1478013078,0,7b92b671,2622068541">这个没见过</d></i>