<?xml version="1.0" encoding="UTF-8"?><i><chatserver>chat.bilibili.com</chatserver><chatid>6532820</chatid><mission>0</mission><maxlimit>500</maxlimit><state>0</state><real_name>0</real_name><source>e-r</source><d p="40.62300,1,25,16777215,1457608035,0,98604491,1671926773">看着心好痛</d><d p="54.47300,1,25,6830715,1457669543,0,51a7885f,1673174883">全场下来好几次都差点儿摔倒</d><d p="16.66400,1,25,16777215,1457701761,0,9f8e7b9a,1674344777">心疼蛋蛋的腰</d><d p="46.31900,1,25,16777215,1486451027,0,a44f32f7,2968658986">心疼小傻子</d><d p="32.10100,1,25,16777215,1501248828,0,7d4f5d10,3617881512">腰疼的来回走动缓解</d><d p="49.61600,1,25,16777215,1503567759,0,d8fdf8a8,3742803000">一直不太敢看的一场 真的心疼</d></i>