<?xml version="1.0" encoding="UTF-8"?><i><chatserver>chat.bilibili.com</chatserver><chatid>6533317</chatid><mission>0</mission><maxlimit>1000</maxlimit><state>0</state><real_name>0</real_name><source>k-v</source><d p="14.70700,1,25,16777215,1457449898,0,492cac81,1668404149">弹幕呢？</d><d p="5.84700,1,25,16777215,1457449899,0,d14ffe27,1668406403">不错</d><d p="31.41600,5,25,15138834,1457449899,0,d14ffe27,1668408227">最喜欢这旋律</d><d p="10.88600,1,25,15138834,1457449905,0,79295c95,1668420911">前</d><d p="74.39300,1,25,16777215,1457449910,0,183d0346,1668432213">这歌我喜欢</d><d p="21.26900,1,25,16777215,1457449912,0,e6542a5d,1668437017">来了</d><d p="32.67100,1,25,16711680,1457449915,0,93bf39ac,1668443929">柯南童年大爱</d><d p="4.83300,1,25,16777215,1457449917,0,51ea3e5a,1668448505">第一</d><d p="19.78200,1,25,15138834,1457449918,0,b01a60ee,1668450059">前</d><d p="99.00000,1,25,16777215,1457510662,0,b4f85681,1669377847">顶！d=====(￣▽￣*)b</d><d p="158.56700,1,25,16777215,1457510666,0,39cbbda2,1669382323">刚还去回顾了的</d><d p="16.04600,1,25,16777215,1457510679,0,476e10ed,1669400527">来看男神了</d><d p="41.39900,1,25,16777215,1457510681,0,96419124,1669403213">从小看到现在</d><d p="45.81900,1,25,16777215,1457514306,0,b4f85681,1669438733">好听</d><d p="66.41200,1,25,16777215,1457514311,0,a669522b,1669445693">神曲！</d><d p="124.35500,1,25,16777215,1457514313,0,40dfc9fc,1669449621">好喜欢以前的画风QAQ</d><d p="45.38900,1,25,16777215,1457514318,0,b4f85681,1669457359">追了8年了</d><d p="101.52400,1,25,16777215,1457514324,0,b4f85681,1669465621">希望M20给力一点！！</d><d p="162.00700,1,25,16777215,1457514351,0,b4f85681,1669510571">新一男神</d><d p="167.85100,5,25,3342387,1457514354,0,1e93460f,1669516945">要火</d><d p="41.39900,1,25,16777215,1457583165,0,b4f85681,1670986441">赞</d><d p="48.09400,1,25,16777215,1457600700,0,b4f85681,1671674501">没有弹幕啊</d><d p="45.09500,1,25,65535,1457600703,0,3ad717cb,1671677487">男神！！！</d><d p="57.74700,1,25,16777215,1457600719,0,b4f85681,1671704291">time after timer~</d><d p="202.48900,1,25,16777215,1457687147,0,cf5564cd,1673734393">啊雷瓦  共疼洗衣机</d><d p="58.63900,1,25,16777215,1457690778,0,b5e6e5bd,1673801909">bgm是 secret  love</d><d p="155.41300,1,25,15138834,1457690783,0,26dcfe7c,1673813599">弹幕呢</d><d p="50.29800,1,25,15138834,1457690799,0,abe0652d,1673850871">大爱柯南</d><d p="21.94600,5,25,16777215,1457690802,0,e6738d89,1673858899">真相只有一个!</d><d p="85.18600,1,25,16777215,1457690802,0,55fef86d,1673859543">这首歌从我有MP3。。到现在的手机上 都有 10年了吧。。</d><d p="101.33700,1,25,16777215,1457690803,0,55fef86d,1673860693">我爸在夏威夷教我的</d><d p="50.59600,1,25,15138834,1457690805,0,95d7a20f,1673866049">bgm:time after time 仓木麻衣</d><d p="256.18300,1,25,15138834,1457690807,0,95d7a20f,1673871001">业火的向日葵呢</d><d p="111.32200,1,25,16777215,1457690811,0,f6992bf2,1673882323">听到这个曲子顿时热血沸腾</d><d p="19.02200,1,25,9599289,1457690815,0,7c0ec3c2,1673892567">戳进来了 颜表立</d><d p="160.05700,1,25,15138834,1457690816,0,fb7ed93b,1673893115">都在专心看</d><d p="29.56600,1,25,16777215,1457694425,0,1fa6ef80,1673918199">看到柯南就进来了</d><d p="84.89900,1,25,16777215,1457694426,0,3b28bb3c,1673920471">爱的自杀，再问供养</d><d p="165.97500,1,25,16777215,1457694429,0,1fa6ef80,1673930317">怎么感觉就只是吧剧场版的经典片段简单拼起来呢。。。</d><d p="26.41700,1,25,16777215,1457694434,0,c896dd01,1673944171">好棒</d><d p="25.77300,1,25,16777215,1457694443,0,48d7d36e,1673969145">拔刀吧  基德是我的</d><d p="2.46000,1,25,16777215,1457694445,0,a97ab8df,1673976185">入宅曲</d><d p="164.36500,1,25,16777215,1457694447,0,e11edd42,1673983223">贝克街  超经典的哎</d><d p="260.24700,1,18,16777215,1457694448,0,a1a64b95,1673986267">冲矢昴！猫哥最帅</d><d p="20.68700,5,18,6750207,1457694453,0,72dd43bb,1673999723">好棒~</d><d p="47.11700,1,25,255,1457694461,0,1b40a0f1,1674027171">柯南我抱走  基德你们要吧</d><d p="179.12000,1,25,16777215,1457698081,0,5fbcca62,1674089607">新兰永恒</d><d p="32.27500,1,25,16777215,1457698082,0,5100653c,1674092999">古德</d><d p="16.23600,1,25,16777215,1457698085,0,603cc673,1674102631">激动</d><d p="51.25500,1,25,16777215,1457698086,0,603cc673,1674104527">好炫酷</d><d p="167.92400,1,25,16777215,1457698088,0,603cc673,1674110589">静静地看 不说话</d><d p="147.54200,1,25,16777215,1457698090,0,c7a1acda,1674116713">这点最帅！</d><d p="5.71700,1,25,16777215,1457698102,0,dbc9ebee,1674156875">漆黑的追踪者，沉默的十五分钟，贝克街亡灵。。。最爱</d><d p="148.96000,1,25,16777215,1457698105,0,dbc9ebee,1674164769">最爱来了</d><d p="26.59900,1,25,16777215,1457698105,0,a0865e7c,1674165053">我滴童年哇</d><d p="9.23600,1,25,16777215,1457698108,0,28b49be3,1674176871">吓死我声音好大</d><d p="41.44500,1,25,16777215,1457698109,0,28b49be3,1674179635">这番我还没看呢</d><d p="17.33700,1,25,16777215,1457698110,0,acb00750,1674183171">业火向日葵在哪</d><d p="19.63000,1,25,16777215,1457698111,0,c92427a4,1674183495">谁的童年没有我大柯南呢？</d><d p="40.11400,1,25,16777215,1457698111,0,acb00750,1674185577">影院看的向日葵大赞</d><d p="146.81500,1,25,16777215,1457698112,0,28b49be3,1674186791">我关弹屏了！</d><d p="11.00600,1,25,16777215,1457698112,0,580657df,1674187079">贝克街亡灵。迷宫十字路口刷一个</d><d p="55.51400,1,25,16777215,1457698112,0,580657df,1674189739">啊！这里我小时候都哭了</d><d p="75.89200,1,25,16777215,1457698113,0,580657df,1674190841">嫁我啊新一！！！！</d><d p="124.96800,1,25,16777215,1457698114,0,580657df,1674193291">引爆的摩天楼</d><d p="164.08700,1,25,16777215,1457698114,0,580657df,1674195921">我天哪我真要哭了</d><d p="188.05600,1,25,16777215,1457698115,0,580657df,1674197125">站原配啊啊啊啊啊啊啊</d><d p="256.48800,1,25,16777215,1457698120,0,7be698f2,1674215167">来个弹幕</d><d p="151.97700,1,25,11890,1457698126,0,3cede4bc,1674233183">贝克街的亡灵</d><d p="165.57900,5,25,11890,1457698127,0,3cede4bc,1674234893">                迷宫街的十字路口</d><d p="146.58800,5,25,38979,1457698127,0,681b25b7,1674237321">贝克街的亡灵</d><d p="164.83600,5,25,38979,1457698128,0,681b25b7,1674238655">迷宫十字路</d><d p="202.85400,5,25,11890,1457698130,0,3cede4bc,1674245185">             啊啊这点超级感动也只有最好的朋友敢把背后交给别人</d><d p="11.44000,1,25,16777215,1457698130,0,3fb31ce1,1674246305">入宅作+1</d><d p="64.61600,1,25,16777215,1457698138,0,e64dafa5,1674268867">大爱基新～</d><d p="27.00200,1,25,16777215,1457698138,0,a6ee5098,1674270179">我只要工藤新一，其他你们分</d><d p="225.12500,1,25,16777215,1457698139,0,1602499a,1674272607">空手躲子弹233</d><d p="189.34900,1,25,16777215,1457698139,0,65f23544,1674274131">建议mad里人物讲话不要太多，光看嘴动了</d><d p="11.18400,1,25,16777215,1457701742,0,3c4ebbf2,1674281475">常用日语，启蒙大师</d><d p="63.59500,1,25,16777215,1457701745,0,fd44845c,1674293415">基德我的来拔刀</d><d p="51.02900,1,25,16777215,1457701746,0,4a010c4b,1674296115">BGM:TIME AFTER TIME</d><d p="244.13500,1,25,16777215,1457701748,0,fd44845c,1674302673">基德大人</d><d p="288.33300,1,25,16777215,1457701749,0,fd44845c,1674306697">沉默的15</d><d p="219.05900,1,25,16777215,1457701750,0,c86ae1e,1674306989">别和我抢，毛利小五郎是我的</d><d p="193.89400,1,25,16777215,1457701750,0,9f500935,1674307979">水平线上的阴谋</d><d p="234.22900,1,25,16777215,1457701751,0,9f500935,1674310543">沉默的十五分钟</d><d p="253.28100,1,25,16777215,1457701751,0,9f500935,1674312185">第十一个前锋</d><d p="259.28500,1,25,16777215,1457701751,0,9f500935,1674312871">异次元的狙击手</d><d p="246.78000,1,25,16777215,1457701752,0,9f582b90,1674315865">终于看到滑板了</d><d p="1.98300,1,25,16777215,1457701754,0,bf9f6773,1674322709">太美</d><d p="14.38200,1,25,16777215,1457701780,0,8d6149a8,1674407053">还是熟悉的BGM</d><d p="29.88300,1,25,16777215,1457701781,0,8d6149a8,1674408567">最爱工藤君了！！！</d><d p="53.18400,1,25,16777215,1457701781,0,79667250,1674409323">啊啊啊，永远的男神</d><d p="124.36200,1,25,16777215,1457701782,0,8d6149a8,1674414431">静静欣赏</d><d p="58.81400,1,25,14811775,1457701783,0,203ccc8f,1674416359">！！！！！！！</d><d p="201.78100,1,25,16777215,1457701784,0,8d6149a8,1674419595">感谢柯南君多年的陪伴</d><d p="236.46600,1,25,16777215,1457701787,0,60c8605c,1674430547">沉默的十五分钟！！大爱</d><d p="125.84900,1,25,16777215,1457705425,0,4bdde2f,1674547507">前几部不管是剧情还是配乐都好好良心啊555看着好感动</d><d p="125.84900,1,25,16777215,1457705426,0,4bdde2f,1674549819">这几年某导演真是一直在毁柯南哼！</d><d p="149.54400,1,25,16777215,1457705427,0,4bdde2f,1674552803">贝克街！！！！</d><d p="166.05400,1,25,16777215,1457705427,0,4bdde2f,1674553849">爱爱爱心意</d><d p="181.75700,1,25,16777215,1457705427,0,4bdde2f,1674554721">新一本尊！！</d><d p="198.21500,1,25,16777215,1457705428,0,4bdde2f,1674556659">毛利爹最帅的时候</d><d p="201.71300,1,25,16777215,1457705428,0,4bdde2f,1674558241">兰园感情羡慕死我了哭</d><d p="222.97000,1,25,16777215,1457705429,0,4bdde2f,1674559577">帅兰出来了</d><d p="22.28500,1,25,16707842,1457705431,0,f8894a06,1674568717">入宅作+1</d><d p="22.24400,1,25,16777215,1457705436,0,5631851d,1674583927">十二年的执念啊</d><d p="108.22500,1,25,16777215,1457705437,0,6b9ba52c,1674588217">这是什么歌好好听</d><d p="269.72000,1,25,16777215,1457705439,0,89eb3ae1,1674593039">没有侦探们的镇魂歌</d><d p="98.63000,1,25,16777215,1457705439,0,9ee7afd5,1674595937">竟然沒彈幕</d><d p="13.62000,1,25,16777215,1457705441,0,8e65dbdf,1674600443">蜜汁感动</d><d p="117.91700,1,25,16777215,1457705448,0,b4507472,1674623923">很早以前看的几部剧场版都忘了</d><d p="136.37500,1,25,16777215,1457705449,0,b4507472,1674627141">对啊，以前的画风挺好看的</d><d p="150.16700,1,25,16777215,1457705449,0,b4507472,1674627885">这几部我都看哭了</d><d p="171.04200,1,25,16777215,1457705450,0,b4507472,1674629975">当就是精彩部分的剪辑啊…没看标题吗</d><d p="51.01300,1,25,15138834,1457705450,0,3d176000,1674630081">引爆摩天大楼</d><d p="95.47500,1,25,8700107,1457705450,0,943298df,1674631121">慢慢都是回忆</d><d p="61.09100,1,25,15138834,1457705451,0,3d176000,1674631675">sishisig</d><d p="66.73300,5,25,11890,1457705451,0,3d176000,1674632609">第十四个目标</d><d p="83.56800,5,25,11890,1457705451,0,3d176000,1674633909">瞳孔中的暗杀者</d><d p="23.39300,1,25,16777215,1457705451,0,786e62bf,1674634185">柯南表示5年前的神话</d><d p="218.79200,1,25,16777215,1457705451,0,b4507472,1674634271">哈哈哈小兰空手躲子弹那段吧</d><d p="103.30500,5,25,11890,1457705451,0,3d176000,1674635133">世纪末的魔术师</d><d p="226.75000,1,25,16777215,1457705452,0,b4507472,1674636273">每次剧场版小兰都要秀空手道 柯南都要秀特技</d><d p="232.04200,1,25,16777215,1457705452,0,b4507472,1674637013">逆天的鼻子！！！</d><d p="150.62700,5,25,11890,1457705452,0,3d176000,1674638607">贝克街的亡灵</d><d p="277.08300,1,25,16777215,1457705453,0,b4507472,1674639719">虽然剧场版剧情越做越差了，不过陪伴这么多年还是很感动，谢谢</d><d p="166.57900,5,25,11890,1457705453,0,3d176000,1674640255">迷宫的十字路口</d><d p="0.00000,1,25,16777215,1457705454,0,5f9b8e64,1674641757">bobobo</d><d p="187.63900,5,25,11890,1457705453,0,3d176000,1674641885">银翼的魔术师</d><d p="193.07300,5,25,11890,1457705454,0,3d176000,1674642767">水平线上的阴谋</d><d p="210.53400,5,25,11890,1457705454,0,3d176000,1674644359">漆黑的追踪者</d><d p="233.01100,5,25,11890,1457705455,0,3d176000,1674647209">沉默的十五分钟</d><d p="243.73900,5,25,11890,1457705455,0,3d176000,1674648197">绝海的侦探</d><d p="249.68300,5,25,11890,1457705456,0,3d176000,1674649587">呸刚刚打错了，这个是 第十一个前锋</d><d p="260.31800,5,25,11890,1457705456,0,3d176000,1674650567">异次元的狙击手</d><d p="31.12500,1,25,16777215,1457705459,0,b00a0b3,1674661007">看柯南的时候是最开心的</d><d p="75.09500,1,25,16777215,1457709067,0,654830fe,1674685301">硬币走起</d><d p="246.61600,1,25,16777215,1457709068,0,f8a9a3d2,1674688947">艾玛我看哭了QAQ</d><d p="227.96200,5,25,15138834,1457709070,0,654830fe,1674694271">每部剧场版看过不少于5遍</d><d p="117.21600,5,25,14811775,1457709070,0,6f5f3000,1674694389">time aftet time和seacre of my heart 最喜欢了</d><d p="253.74600,1,25,16777215,1457709070,0,b3690b52,1674696261">第十一个前锋</d><d p="263.45200,5,25,16777215,1457709071,0,b3690b52,1674697587">异次元的狙击手</d><d p="148.93500,5,25,14811775,1457709071,0,6f5f3000,1674697709">最爱贝克街的亡灵</d><d p="165.93200,5,25,14811775,1457709071,0,6f5f3000,1674699171">迷宫十字路口</d><d p="246.87500,1,25,16777215,1457709071,0,d4fdf68a,1674699463">莫名的虐…</d><d p="187.99000,5,25,14811775,1457709072,0,6f5f3000,1674701053">天空中的遇难船</d><d p="207.12400,5,25,14811775,1457709072,0,6f5f3000,1674702591">绀碧之棺</d><d p="234.57000,5,25,14811775,1457709073,0,6f5f3000,1674705331">沉默的十五分钟</d><d p="173.26500,1,25,16777215,1457709074,0,b66fb72a,1674708039">迷宫的十字路口</d><d p="98.56600,1,25,16777215,1457709116,0,facd1f4c,1674830213">中间还差一个M3世纪末的魔术师啊</d><d p="125.07100,1,25,15138834,1457712727,0,855a3e0e,1674855843">引爆摩天楼</d><d p="148.36500,5,25,15138834,1457712727,0,855a3e0e,1674857225">贝克街的亡灵</d><d p="164.06600,5,25,15138834,1457712728,0,855a3e0e,1674858367">迷宫的十字路</d><d p="95.55900,1,25,16777215,1457712735,0,234e3c18,1674876961">ttt</d><d p="102.86400,1,25,16777215,1457712736,0,234e3c18,1674877259">dsw</d><d p="234.42300,1,25,16777215,1457712774,0,b06e3cee,1674953567">最爱。</d><d p="34.25100,1,25,16777215,1457712775,0,d0d806d8,1674955139">BGM好评</d><d p="36.79200,1,25,16777215,1457744953,0,d9fa2c66,1675288857">基德基德</d><d p="66.87500,1,25,16777215,1457744954,0,d9fa2c66,1675289503">永远的男神</d><d p="187.45800,1,25,16777215,1457744956,0,d9fa2c66,1675292065">基德sama</d><d p="266.03500,1,25,16777215,1457744958,0,3026e92b,1675295253">爱爱爱爱。</d><d p="279.11500,1,25,16777215,1457744958,0,3026e92b,1675295511">真想永远只有一个</d><d p="22.21100,1,25,16777215,1457744960,0,f412caa7,1675297907">凶手是谁</d><d p="70.94300,1,25,16777215,1457752288,0,362caddb,1675541501">神曲</d><d p="235.79300,1,25,16777215,1457752292,0,362caddb,1675551429">大爱啊</d><d p="237.43700,1,25,16777215,1457755922,0,b4f85681,1675636305">泪目</d><d p="31.38800,1,25,16777215,1457777174,0,b4f85681,1676678039">凶手是我</d><d p="280.76600,1,25,16777215,1457957316,0,70ff641d,1682305505">侦探们的镇魂歌最好看 看了三四遍饿了</d><d p="66.75400,1,25,16777215,1459001436,0,b4f85681,1709177457">感动</d><d p="11.34700,1,25,16777215,1459001443,0,939c8308,1709201101">初中净看这个了 害的没学好</d><d p="92.64700,1,25,16777215,1459001444,0,939c8308,1709208005">因为我比这个世界上的任何人都爱你</d><d p="186.54400,1,25,16777215,1459001452,0,b4f85681,1709234231">每一部都看了不下两遍</d><d p="167.99500,5,25,16777215,1459051932,0,780ba4e4,1710388961">迷宫的十字路口</d><d p="64.37900,1,25,16777215,1459051951,0,f944facc,1710443679">死神柯南 是我的 不服的去死吧(҂⌣̀_⌣́)</d><d p="77.64300,5,25,16777215,1459065852,0,a5a66387,1711108473">说难看的你可以滚了↑</d><d p="184.78200,1,25,16711680,1459803923,0,abe0652d,1733836949">大爱柯南，柯南我是抱走了记得留给你们</d><d p="38.56600,1,25,15138834,1460635688,0,4285264e,1758860415">新兰一生推！！！</d><d p="66.45300,1,25,15138834,1460635688,0,4285264e,1758863383">弹幕这么少不科学！</d><d p="114.70400,1,25,15138834,1460635689,0,4285264e,1758865979">嘤嘤嘤泪目</d><d p="159.96000,1,25,15138834,1460635691,0,4285264e,1758868771">每部都有泪点好伐</d><d p="209.46500,1,25,15138834,1460635692,0,4285264e,1758871511">绀碧之棺</d><d p="259.73600,1,25,15138834,1460635693,0,4285264e,1758874539">QAQQQQQQQQQQ我大本命嗷嗷嗷嗷嗷嗷</d><d p="53.31200,1,25,16777215,1460635704,0,43f07b6e,1758904637">追了好多年！</d><d p="50.20300,5,25,16777215,1460782907,0,df179da,1763566079">柯南：就剪你喜欢的颜色吧</d><d p="50.20300,5,25,16777215,1460782907,0,df179da,1763567043">我会一直在这里陪着你</d><d p="11.66200,4,25,255,1460782907,0,8d675f09,1763569661">截图留念</d><d p="125.85100,5,25,15138834,1462810362,0,9e0548fe,1835959437">哀  你不会孤单  虽然我们并不在同一个次元  但你却一直在我心中</d><d p="166.43900,1,25,16777215,1463029285,0,679b4c0b,1841198241">以前的剧场版多良心啊</d><d p="116.68800,1,25,16777215,1463029288,0,48654b96,1841205031">蜜汁泪目</d><d p="241.01700,1,25,16777215,1463029290,0,48654b96,1841210507">泪目</d><d p="123.32300,1,25,16777215,1463029294,0,a7328b6b,1841219985">在夏威夷什么都能学到</d><d p="172.15300,1,25,16777215,1463062212,0,6204f5ca,1842487981">平次的剑术不是盖的</d><d p="55.65600,1,25,16777215,1463152276,0,8b3e558,1845658433">16年了，新一……</d><d p="62.83500,1,25,16777215,1463483235,0,99bfbe06,1857738131">M2这里超级帅！</d><d p="148.16400,1,25,16777215,1463483237,0,99bfbe06,1857742851">贝克街！</d><d p="54.40700,1,25,16777215,1463490564,0,e2aadbc3,1858119159">引爆摩天楼</d><d p="65.91100,1,25,16777215,1463490564,0,e2aadbc3,1858119809">14号目标</d><d p="99.01900,1,25,16777215,1463490564,0,e2aadbc3,1858121565">瞳孔中的暗杀者</d><d p="155.11400,1,25,16777215,1463490565,0,e2aadbc3,1858124465">贝克街的亡灵</d><d p="168.99000,1,25,16777215,1463490565,0,e2aadbc3,1858125217">迷宫十字路</d><d p="196.73800,1,25,16777215,1463490566,0,e2aadbc3,1858126707">银翼的奇术师</d><d p="219.69000,1,25,16777215,1463490566,0,e2aadbc3,1858127945">异次元狙击手</d><d p="35.71100,1,18,16777215,1463760749,0,d64603b0,1867526127">滚筒洗衣机233333</d><d p="59.23300,1,25,16711680,1464700195,0,ee617671,1910648445">这歌当铃声用了快半年了 刚才以为手机响了</d><d p="226.13200,1,25,16777215,1464840757,0,a97ab8df,1915763097">战栗的音乐普呢？</d><d p="258.88000,1,25,16777215,1466086220,0,6d92e1ff,1964960613">逆天 这画面</d><d p="121.25400,1,25,16777215,1466478698,0,36ea7b4a,1981210267">bgm仓木麻衣timeaftertime，京都那个剧场版的主题曲</d><d p="132.39900,1,25,16777215,1466510911,0,d9bbab1,1982894381">胖小菇，我比世界上任何人都更爱你</d><d p="11.97000,1,25,16777215,1466777455,0,b538d17f,1993839187">弹幕你</d><d p="47.35000,5,25,16711680,1466777456,0,b538d17f,1993841865">柯南</d><d p="94.34700,5,25,16711680,1466777456,0,b538d17f,1993845445">因为喜欢你</d><d p="158.46600,5,25,16711680,1466777457,0,b538d17f,1993850453">福尔摩斯</d><d p="173.96500,5,25,16711680,1466777458,0,b538d17f,1993851725">迷宫的十字路口</d><d p="192.60500,5,25,16711680,1466777458,0,b538d17f,1993853047">基德</d><d p="212.35100,5,25,16711680,1466777458,0,b538d17f,1993854609">帅</d><d p="233.96400,5,25,16711680,1466777459,0,b538d17f,1993857509">沉默的十五分钟</d><d p="161.26000,5,25,14811775,1467036618,0,f5109797,2006202789">最喜欢的剧场版</d><d p="74.57300,1,25,16777215,1467036653,0,68bc130f,2006357397">第十四号猎物</d><d p="89.43300,1,25,16777215,1467036653,0,68bc130f,2006358487">黑暗中的狙击手</d><d p="128.96100,1,25,16777215,1467036654,0,68bc130f,2006361433">通往天国的倒数计时</d><d p="189.25600,1,25,16777215,1467453998,0,d3b07aed,2026072893"> 说遇难船的回来我不打残你</d><d p="266.10100,5,25,65433,1467454000,0,d3b07aed,2026080973"> 欢迎大家收看牛顿哭瞎在棺材里系列</d><d p="235.57800,1,25,16777215,1467511805,0,edd0a3a8,2029075669">沉默的十五分钟</d><d p="190.65800,1,25,16777215,1467533072,0,b15dc7ea,2030870499">我的手机来电铃声是名侦探柯南的主题曲已经有7年了</d><d p="283.52500,1,25,16777215,1467533073,0,b15dc7ea,2030877763">每个镜头都很熟悉</d><d p="195.14400,1,25,16777215,1467536735,0,ba8390ea,2031171567">毛利大叔战胜柯南 这部不错</d><d p="58.18800,1,25,16777215,1467540361,0,6482a9c7,2031292311">神曲</d><d p="36.45900,1,25,15138834,1467871333,0,bd29c405,2049271379">没人要服部的话他就是我的了</d><d p="40.00600,1,25,16777215,1467871355,0,43f2e728,2049365499">哈哈哈哈，所有的我都看完了。</d><d p="58.46500,1,25,16777215,1467871356,0,43f2e728,2049367649"> 引爆摩天大楼</d><d p="148.32600,1,25,16777215,1467871358,0,43f2e728,2049375865">贝克街的亡灵</d><d p="233.93800,1,25,16777215,1467871359,0,43f2e728,2049382625">沉默的15分钟</d><d p="51.03600,1,25,16777215,1468422697,0,cf63d198,2081952247">time after time！</d><d p="151.34700,1,25,16777215,1468422699,0,cf63d198,2081961433">贝克街的亡灵！</d><d p="236.35700,1,25,16777215,1468642363,0,cb7579cd,2094148849">最爱的十五分</d><d p="117.30800,1,25,16777215,1468725102,0,10f0e518,2099156773">这炸我出来了</d><d p="168.19800,1,25,16751001,1468725103,0,10f0e518,2099161721">迷宫的十字路口</d><d p="182.62600,1,25,16751001,1468725104,0,10f0e518,2099163429">银翼的魔术师</d><d p="193.12300,1,25,16751001,1468725104,0,10f0e518,2099164927">水平线上的阴谋</d><d p="199.81000,1,25,16751001,1468725105,0,10f0e518,2099167217">绀碧之棺</d><d p="213.98800,1,25,16751001,1468725105,0,10f0e518,2099169185">漆黑的追踪者</d><d p="232.35100,1,25,16751001,1468725106,0,10f0e518,2099171595">沉默的十五分钟</d><d p="244.13200,1,25,16751001,1468725106,0,10f0e518,2099173177">第十一个前锋</d><d p="259.53400,1,25,16751001,1468725106,0,10f0e518,2099175461">异次元的狙击手</d><d p="112.75500,1,18,16777215,1468944749,0,8bb6bd40,2114622917">time after time</d><d p="127.50400,1,25,16777215,1468944753,0,3dccac6a,2114636017">速度与激情</d><d p="80.62600,1,25,16777215,1468984304,0,a82e4379,2115927713">麻衣^_^</d><d p="102.08400,1,25,16777215,1468984304,0,a82e4379,2115928727">回忆</d><d p="160.79200,1,25,16777215,1468984305,0,a82e4379,2115932999">贝克街。</d><d p="177.20900,1,25,16777215,1468984306,0,a82e4379,2115934381">这个暑假要好好复习一下</d><d p="24.36800,5,25,15138834,1469070713,0,b182406b,2121339359">绝海的侦探，异次元的狙击手</d><d p="48.54700,5,25,15138834,1469070714,0,b182406b,2121342457">爆破摩天大楼</d><d p="61.20800,5,25,15138834,1469070714,0,b182406b,2121343925">第十四个目标</d><d p="84.15200,5,25,15138834,1469070714,0,b182406b,2121346571">瞳孔中的暗杀者</d><d p="103.87300,5,25,15138834,1469070715,0,b182406b,2121348671">世纪末的魔术师</d><d p="116.60000,5,25,15138834,1469070715,0,b182406b,2121350089">通往天国的倒计时</d><d p="147.15500,5,25,15138834,1469070716,0,b182406b,2121352715">贝克街的亡灵</d><d p="163.22600,5,25,15138834,1469070716,0,b182406b,2121354315">迷宫的十字路口</d><d p="186.66200,5,25,15138834,1469070717,0,b182406b,2121356305">银翼的魔术师</d><d p="193.19300,5,25,15138834,1469070717,0,b182406b,2121357345">水平线上的阴谋</d><d p="208.30000,5,25,15138834,1469070717,0,b182406b,2121359199">漆黑的追踪者</d><d p="231.92100,5,25,15138834,1469070718,0,b182406b,2121361547">沉默的十五分钟</d><d p="243.40900,5,25,15138834,1469070718,0,b182406b,2121363455">第十一位前锋（超喜欢的）</d><d p="259.69400,5,25,15138834,1469070719,0,b182406b,2121365125">异次元的狙击手</d><d p="278.64200,5,25,15138834,1469070719,0,b182406b,2121368317">沉默的十五分钟</d><d p="237.02700,5,25,15138834,1469157065,0,e58c2f28,2126445601">啊啊啊啊大爱这部</d><d p="280.39800,1,25,16777215,1469592740,0,70d914b4,2154862291">？侦探们的镇魂歌呢？战栗的乐谱呢？</d><d p="237.30700,5,25,15138834,1469959570,0,e822833e,2180696301">沉默的十五分钟</d><d p="151.18200,1,25,16777215,1470286897,0,7e3d0c34,2203724469">最爱贝克街</d><d p="80.36700,1,25,16777215,1470560739,0,fd466a42,2222562983">马上泪目了卧槽</d><d p="148.60200,1,25,16777215,1470560741,0,fd466a42,2222571777">贝克街的亡灵大爱啊啊</d><d p="273.76600,1,25,16777215,1470712279,0,2e3657de,2232227895">没有战栗的乐谱</d><d p="57.87700,1,25,16777215,1470712280,0,65a38c56,2232235223">第一部，我的初心。新兰一生</d><d p="71.01200,1,25,16777215,1470712302,0,f53a94a1,2232333385">麻衣！！！</d><d p="175.49400,1,25,16777215,1470712304,0,f53a94a1,2232343417">十字路！！</d><d p="206.15600,1,25,16777215,1470712304,0,f53a94a1,2232345819">绀碧之棺！！！</d><d p="248.30400,1,25,16777215,1470712305,0,f53a94a1,2232349051">我爱这个剪辑！</d><d p="264.93700,1,25,16777215,1470712305,0,f53a94a1,2232350387">冲矢昂</d><d p="65.85100,1,25,16777215,1470744528,0,526de061,2235154363">这部我小学两年级看的…看完做噩梦了</d><d p="84.15100,1,25,16777215,1470802339,0,defa9a17,2240839275">爸爸在我小时候在夏威夷教我的</d><d p="148.23800,5,25,16777215,1470802341,0,defa9a17,2240846599">贝克街的亡灵</d><d p="245.71100,5,25,16777215,1470802343,0,defa9a17,2240857535">这个超帅！！！！任意球！！！</d><d p="153.28500,1,25,16777215,1470981772,0,5edab61,2252782105">这个百看不厌啊</d><d p="39.17600,1,25,16777215,1471270253,0,d0a32e36,2272379819">十字路口，异次元的狙击手，贝克街，算了不数了，每一部都好看</d><d p="78.99200,1,25,16777215,1471277522,0,ef2d2e79,2272769191">好帅气</d><d p="144.75600,1,25,16777215,1471529434,0,24ef17d2,2289409971">花舞的街道吧？</d><d p="20.09000,1,25,16777215,1471950467,0,d13b2aff,2316816813">这音乐真是激动人心</d><d p="74.19300,1,25,16777215,1471950468,0,8f6ceefa,2316824785">BGM：十字迷宫的ED不谢..........</d><d p="164.93500,1,25,16777215,1471950470,0,8f6ceefa,2316832575">亡灵最经典</d><d p="158.61300,1,25,16777215,1471950470,0,d13b2aff,2316834219">贝克街的亡灵  一直是我的幻想世界 在里面生活已经有8年了</d><d p="232.02700,1,25,16777215,1472213313,0,7ec6ab23,2334201813">沉默的十五分钟，这个看哭</d><d p="23.84400,1,25,16777215,1472648971,0,b7518abb,2360286613">异次元的狙击手那个才6</d><d p="263.21900,1,25,16777215,1472648976,0,b7518abb,2360304629">异次元的狙击手，爱</d><d p="261.40000,1,25,16777215,1472904513,0,49411fe6,2370779929">表白我秀！！！！！</d><d p="68.53600,1,25,16777215,1473567152,0,5529f932,2394853409">听这首歌好多年</d><d p="57.23400,1,25,16777215,1473570069,0,b3fdaba7,2395015557">我腰服部！</d><d p="13.28100,1,25,16777215,1475323693,0,c0139d8f,2479336813">大萌迷宫的十字路口</d><d p="93.41100,1,25,16777215,1475381576,0,4e5a5c0f,2483668765">瞳孔中的暗杀者。</d><d p="49.99000,1,25,16777215,1475381578,0,4e5a5c0f,2483677199">引爆摩天大楼。</d><d p="124.54200,1,25,16777215,1475388167,0,7407c21d,2484551397">mustang</d><d p="116.17900,1,25,16777215,1475388171,0,d75b74b4,2484569219">小哀完成的计算w</d><d p="261.01000,1,25,16777215,1475388173,0,d75b74b4,2484822847">昴哥ww</d><d p="96.72600,5,25,13369344,1475456994,0,aa5a0b3d,2490745775">BGM爱的供养柔情版</d><d p="98.20000,1,25,16777215,1475460639,0,305f1ec1,2490910283">想到了万能夏威夷</d><d p="252.09000,1,25,16777215,1475633420,0,305f1ec1,2504659895">感动</d><d p="118.33500,1,25,16777215,1476360492,0,f7c222db,2549900027">time after time</d><d p="34.30100,1,25,16777215,1476695132,0,a26e9290,2563114145">BGM好好听</d><d p="117.49200,1,25,16777215,1476695134,0,a26e9290,2563117123">基德2333</d><d p="195.48500,1,25,16777215,1476695135,0,a26e9290,2563120063">代娇在我看了近一二十年的动漫向你表白</d><d p="39.96500,1,25,16777215,1477408277,0,84c5caa8,2594935121">承包灰原哀</d><d p="102.21200,1,25,16777215,1478311811,0,79e18b63,2632689001">弹幕素质低</d><d p="255.16100,1,25,16777215,1478311814,0,79e18b63,2632693903">牛顿的棺材板要压不住了</d><d p="103.88900,1,25,16777215,1478445069,0,f83aff18,2639376855">神tm夏威夷</d><d p="204.08800,1,25,16777215,1479024240,0,6ab302be,2658358027">要复习的我告诉你都没有资源了</d><d p="258.96300,1,25,16777215,1479024241,0,6ab302be,2658361147">画风。。。</d><d p="87.90500,1,25,16777215,1479024241,0,8f2518b9,2658364041">BGM好评</d><d p="122.84100,1,25,16777215,1479063831,0,d22690f,2660384647">这是什么画风</d><d p="77.40100,1,25,16777215,1479809210,0,3c47f8e4,2684984035">这歌已经会唱</d><d p="39.69200,1,25,16777215,1479809218,0,ed1ee119,2685006543">我柯南大哥呐？</d><d p="53.43700,5,25,6749952,1479809219,0,ed1ee119,2685008609">柯南：剪你最喜欢的吧</d><d p="119.61000,5,25,6749952,1479812820,0,ed1ee119,2685012239">哎我还是喜欢柯兰组合</d><d p="163.10800,5,25,6749952,1479812821,0,ed1ee119,2685014337">弄我柯南者 死！</d><d p="163.10800,5,25,10066329,1479812821,0,ed1ee119,2685014947">弄我柯南者 死！</d><d p="163.10800,5,25,255,1479812821,0,ed1ee119,2685015539">弄我柯南者 死！</d><d p="163.10800,5,25,16711935,1479812821,0,ed1ee119,2685016285">弄我柯南者 死！</d><d p="241.39800,5,25,16711935,1479812823,0,ed1ee119,2685020283">哎</d><d p="147.22900,1,25,16777215,1480096930,0,c8b001e7,2694003085">我爸在夏威夷教我的</d><d p="49.78000,1,25,16777215,1480226550,0,5a56e965,2698923901">鸡皮疙瘩都起来了</d><d p="164.36900,1,18,16777215,1482710919,0,d3f07f75,2783284497">迷宫的十字路口</d><d p="236.21400,1,25,16777215,1484525316,0,2fd94245,2853167517">大爱</d><d p="176.83500,1,25,0,1485187940,0,7573216,2890423502">新兰永恒 平和永恒</d><d p="146.06200,1,25,16777215,1485327824,0,44d5de1a,2897825398">贝克街的亡灵</d><d p="164.48800,1,25,16777215,1485346104,0,3aa96ff,2899194502">站平新</d><d p="46.18400,1,25,16711680,1488679806,0,921805c1,3070012806">基德KID</d><d p="86.16400,1,25,16711680,1488679807,0,921805c1,3070015610">瞳孔中的暗杀者！</d><d p="111.26400,1,25,16711680,1488679808,0,921805c1,3070017710">这里我男神基德sama！</d><d p="152.08400,1,25,16711680,1488679808,0,921805c1,3070019772">满满的回忆啊！！</d><d p="176.10400,1,25,16711680,1488679809,0,921805c1,3070020998">投币了！</d><d p="182.44400,1,25,16711680,1488679809,0,921805c1,3070021902">表白我男神基德</d><d p="191.06400,1,25,16711680,1488679809,0,921805c1,3070022872">银翼的魔术师</d><d p="264.36400,1,25,16711680,1488679811,0,921805c1,3070028334">业火的向日葵！</d><d p="166.15900,5,25,16777215,1489064942,0,27afb2a9,3083792594">迷宫的十字路口</d><d p="166.43300,5,25,15138834,1489493318,0,a3bdfd59,3101707788">迷宫的十字路口</d><d p="95.15300,1,25,15138834,1489939960,0,c8d0196,3121057872">每一部都要吃狗粮╭(°A°`)╮</d><d p="285.83300,1,25,16777215,1489942872,0,c4b9a2ab,3121138978">业火的向日葵那</d><d p="101.65500,1,25,16777215,1489942873,0,c4b9a2ab,3121140460">世纪末的魔术师</d><d p="154.73000,1,25,16777215,1490188183,0,a841209d,3129221514">浴血奋战</d><d p="167.29400,1,25,14811775,1490188184,0,a841209d,3129224596">平和一生推</d><d p="71.99300,1,25,16777215,1490710229,0,9b444482,3151490418">截图！！！！！</d><d p="195.09100,4,25,16711680,1490710231,0,9b444482,3151500970">毛利小五郎认真起来还是很厉害的也很帅</d><d p="51.19800,1,25,16777215,1491829742,0,2d2da68d,3209654354">新兰一生推</d><d p="184.10200,1,25,16777215,1492506320,0,1189586d,3240069092">新兰永恒</d><d p="164.09100,1,25,16777215,1492791128,0,d233314d,3253636906">最爱迷宫的十字路口!</d><d p="114.80700,4,25,41194,1494158903,0,8c3bd0c5,3326779544">KID KID KID</d><d p="182.77000,4,25,41194,1494158905,0,8c3bd0c5,3326786294">KID KID KID KID</d><d p="110.86000,1,25,16777215,1494752726,0,7e61436d,3356360172">唐红的恋歌</d><d p="113.61300,1,25,16777215,1495774905,0,79f15fc5,3406404308">怪盗基德</d><d p="277.74300,1,25,16777215,1496509281,0,a42e1f98,3429359435">说剧场版越来越差的，自重</d><d p="152.01000,1,25,16777215,1496711357,0,48e31f1d,3434715129">智商也在线</d><d p="236.69600,1,25,16777215,1498802533,0,7c95b6f,3505495671">沉默的十五分钟</d><d p="29.07500,1,25,0,1499263846,0,1e18db91,3525226799">通往天国的倒计时</d><d p="231.04700,1,25,16777215,1499703130,0,3d4c971f,3544345703">东京悍妇</d><d p="288.49900,1,25,16777215,1499703131,0,3d4c971f,3544349052">乐谱没有</d><d p="42.50300,1,25,16777215,1500520416,0,feead175,3580873976">平次是我的！</d><d p="141.17300,1,25,16777215,1500520528,0,feead175,3580880468">光彦这里也很帅啊</d><d p="163.70400,1,25,16777215,1500520727,0,feead175,3580891943">服部平次最帅！！！</d><d p="242.13400,1,25,16777215,1500520812,0,feead175,3580896593">我新兰啊哭哭</d><d p="138.54100,1,25,16777215,1500724496,0,d28d882f,3591183317">听过新兰，柯哀，柯兰是什么鬼</d><d p="164.86900,1,25,16777215,1500976657,0,5b81fd29,3603496300">天哪樱花的十字路口</d><d p="110.25700,1,25,16777215,1501083352,0,94beb01d,3609435513">世纪末的魔术师</d><d p="149.27200,1,25,16777215,1501092958,0,e91cbc47,3609917479">最好看的一部</d><d p="18.79900,1,25,0,1501128743,0,e2e02474,3610968644">进度条加油</d><d p="31.13000,1,25,0,1501128755,0,e2e02474,3610969479">狙击手</d><d p="49.92400,1,25,0,1501128774,0,e2e02474,3610970751">基德也在吗</d><d p="94.01800,1,25,0,1501128751,0,e2e02474,3610973720">赞赞</d><d p="185.66500,1,25,0,1501128910,0,e2e02474,3610979961">柯南骑滑板帅</d><d p="41.68100,1,25,16777215,1501431992,0,217d53ca,3627767786">我要服部平次</d><d p="45.69600,1,25,16777215,1501460335,0,7478aa75,3628346400">承包小哀</d><d p="286.23600,1,25,16777215,1501650726,0,94c103e7,3638603460">的确剧场版越做越差了</d><d p="50.35600,1,25,16777215,1501685630,0,da681344,3641244891">bgm响起泪目</d><d p="15.70100,1,25,16777215,1501781357,0,d79f5fda,3646622122">那么问题来了，今年，柯南小雪毕业了吗</d><d p="230.04200,5,25,16777215,1501926503,0,7b2917f7,3653879924">漆黑的追踪者</d><d p="234.68600,5,25,16777215,1501926560,0,7b2917f7,3653881756">最喜欢的，沉默的十五分钟</d><d p="4.24700,1,25,16777215,1501995774,0,74633160,3657268410">超棒啊</d><d p="20.28700,1,25,16777215,1501995805,0,74633160,3657270736">帅，贝克街的灵亡炒鸡好看</d><d p="45.11800,1,25,16777215,1501995845,0,74633160,3657273725">异次元的狙击手也好看，帅死我了</d><d p="98.53400,1,25,16777215,1501995905,0,74633160,3657278278">超级棒</d><d p="117.05000,1,25,15138834,1501995850,0,74633160,3657280409">通往天国的倒计时</d><d p="147.93900,1,25,15138834,1501995972,0,74633160,3657283184">贝克街的灵亡</d><d p="165.26100,1,25,15138834,1501995994,0,74633160,3657284883">迷宫的十字路口</d><d p="183.09500,1,25,15138834,1501996029,0,74633160,3657287416">银翼的魔术师</d><d p="195.63800,1,25,15138834,1501996048,0,74633160,3657288873">水平线上的阴谋</d><d p="202.59300,1,25,15138834,1501996069,0,74633160,3657290397">绀碧之馆</d><d p="210.10100,1,25,15138834,1501996082,0,74633160,3657291384">漆黑的追踪者</d><d p="216.58700,1,25,15138834,1501996108,0,74633160,3657293206">才发现我好熟悉柯南♥帅</d><d p="232.67100,1,25,15138834,1501996107,0,74633160,3657295281">沉默的十五分钟</d><d p="244.53200,1,25,15138834,1501996143,0,74633160,3657297011">第11名先锋</d><d p="255.83700,1,25,15138834,1501996179,0,74633160,3657298422">回忆起了好多</d><d p="262.62000,1,25,15138834,1501996192,0,74633160,3657299452">异次元的狙击手</d><d p="4.50200,1,25,16777215,1502011374,0,74633160,3658359815">怀念啊，超级棒</d><d p="27.71000,1,25,15138834,1502011407,0,74633160,3658362256">异次元的狙击手</d><d p="37.27600,1,25,15138834,1502011411,0,74633160,3658363845">听到这个音乐就开心</d><d p="51.43200,1,25,15138834,1502011467,0,74633160,3658366485">引爆摩天楼</d><d p="63.29300,1,25,15138834,1502011494,0,74633160,3658368335">第十四个目标</d><d p="84.66700,1,25,15138834,1502011525,0,74633160,3658370595">瞳孔中的暗杀者</d><d p="97.72300,1,25,15138834,1502011528,0,74633160,3658373011">因为我比地球上的任何一个人都要喜欢你</d><d p="106.59700,1,25,15138834,1502011491,0,74633160,3658374284">世纪末的魔术师</d><d p="117.43400,1,25,15138834,1502011594,0,74633160,3658375749">通往天国的倒计时</d><d p="147.72500,1,25,15138834,1502011638,0,74633160,3658378871">贝克街的灵亡，最爱啊</d><d p="164.23600,1,25,15138834,1502011661,0,74633160,3658380562">迷宫的十字路口</d><d p="191.73900,1,25,15138834,1502012031,0,74633160,3658412183">真的看了这个超级感动</d><d p="48.42100,1,25,15138834,1502012287,0,74633160,3658423974">剪你最喜欢的颜色吧</d><d p="53.09800,1,25,41194,1502101729,0,74633160,3663169742">引爆摩天楼~</d><d p="62.16100,1,25,41194,1502101693,0,74633160,3663171084">第十四个目标</d><d p="83.45100,1,25,41194,1502101722,0,74633160,3663173179">瞳孔中的暗杀者</d><d p="92.24000,1,25,41194,1502101789,0,74633160,3663174063">怀念啊</d><d p="107.08600,1,25,41194,1502101845,0,74633160,3663175857">世纪末的魔术师</d><d p="119.80100,1,25,41194,1502101864,0,74633160,3663177185">通往天国的倒计时</d><d p="147.87300,1,25,41194,1502101907,0,74633160,3663180197">贝克街的亡灵，炒鸡喜欢</d><d p="164.68300,1,25,41194,1502101901,0,74633160,3663181914">迷宫的十字路口</d><d p="183.96700,1,25,41194,1502101876,0,74633160,3663184074">银翼的魔术师，告白篇</d><d p="193.52500,1,25,41194,1502101978,0,74633160,3663185181">水平线上的阴谋</d><d p="200.26600,1,25,41194,1502101907,0,74633160,3663186235">绀碧之棺</d><d p="209.78100,1,25,41194,1502102010,0,74633160,3663187476">漆黑的追踪者</d><d p="231.49600,1,25,41194,1502102039,0,74633160,3663189457">沉默的十五分钟</d><d p="243.69800,1,25,41194,1502102068,0,74633160,3663191624">第十一个前锋</d><d p="46.94500,1,25,16777215,1502114684,0,f1812289,3664161558">bgm全是回忆</d><d p="72.72500,1,25,16777215,1502160608,0,f1812289,3665775209">洗衣机</d><d p="195.77600,1,25,16777215,1502160749,0,f1812289,3665782254">帅气</d><d p="218.62900,1,25,16777215,1502160772,0,f1812289,3665783647">疼</d><d p="238.87200,1,25,16777215,1502160792,0,f1812289,3665784774">沉默的十五分钟</d><d p="251.15600,1,25,16777215,1502160718,0,f1812289,3665785477">这个滑板很帅</d><d p="281.75300,1,25,16777215,1502160817,0,f1812289,3665787310">侦探们的镇魂歌也超棒</d><d p="104.85200,1,25,16777215,1502547271,0,bb094dab,3687375313">漏了一个呀</d><d p="150.73200,1,25,16777215,1502547307,0,bb094dab,3687379978">贝克街的亡灵！</d><d p="182.99300,1,25,16777215,1502547274,0,bb094dab,3687383563">银翼的魔术师！！！</d><d p="150.48200,1,25,15138834,1502980447,0,81723e47,3711078145">最爱的一部！！！</d><d p="154.70600,1,25,16777215,1503277651,0,9ba70899,3726433874">贝克街！！！</d><d p="249.99600,1,25,16777215,1503277784,0,9ba70899,3726440528">贝克街，第十一名前锋，沉默的十五分钟</d><d p="280.77500,5,25,6830715,1503290624,0,87f2f568,3727242443">战栗的乐谱呢！</d><d p="237.99400,1,25,16777215,1503818981,0,534d3d25,3756313685">最爱  沉默的十五分钟</d><d p="110.43200,1,25,16777215,1503835053,0,7f0926c1,3757453895">神TM的</d><d p="160.54000,1,25,16777215,1503835137,0,7f0926c1,3757459222">福尔摩斯所说的浴血，，</d><d p="114.42000,1,25,16777215,1503911471,0,b74d4bf9,3761212918">time after time</d><d p="149.38200,1,25,16777215,1503935914,0,bf0e91c1,3762990444">贝克街的亡灵</d><d p="82.54200,1,25,16777215,1503974533,0,2199c4e1,3764059086">bgm:花舞街</d><d p="254.11500,1,25,16777215,1504040607,0,e090e0a4,3767885833">教练我也想要这种滑板</d><d p="229.17600,1,25,16777215,1504161592,0,a89fcb1d,3773406986">小兰空手道厉害的很，当然要秀秀</d><d p="21.06300,1,25,16777215,1504192610,0,872af935,3775182323">苦等21</d><d p="38.42600,1,25,16777215,1504366787,0,d5194f03,3782127248">大爱柯南</d><d p="149.11200,1,25,16777215,1504424880,0,a6abaaf8,3784288044">bgm是什么</d><d p="51.73300,1,25,16777215,1504511901,0,2ebca012,3786918518">给新兰打call！！！！！</d><d p="14.36600,1,25,16777215,1504931840,0,23aad851,3798345475">666</d><d p="128.73800,1,25,16777215,1504956231,0,d6c20c71,3799536096">很想冲刷，但都背得了</d><d p="75.55700,1,25,16777215,1505999600,0,5ed8f9b4,3827107369">这首歌叫什么</d><d p="0.55600,1,25,16777215,1506342260,0,5ed8f9b4,3836984531">封面是第几集啊</d><d p="24.98400,1,25,16777215,1506342131,0,5ed8f9b4,3836986055">封面是第几集啊</d><d p="123.64800,1,25,16777215,1506784475,0,e4a9df31,3848051810">这里那一球最帅</d><d p="127.99900,1,25,16777215,1506784318,0,e4a9df31,3848052614">这里那一球最帅</d><d p="158.46300,1,25,16777215,1506784565,0,e4a9df31,3848056321">之前几部都是用心做的，现在后面的都没什么质量可言了</d><d p="195.75400,1,25,16777215,1506784602,0,e4a9df31,3848059167">大叔超帅</d><d p="202.75100,1,25,16777215,1506784639,0,e4a9df31,3848060051">这里看</d><d p="233.72700,5,25,41194,1506784638,0,e4a9df31,3848063136">沉默的十五分钟</d><d p="237.38100,1,25,16777215,1507014292,0,a9625050,3856482873">我也是最喜欢的</d><d p="25.55100,1,25,16777215,1507809976,0,e510488b,3888204599">bgm一出来就好兴奋</d><d p="153.62200,1,25,16777215,1507809940,0,e510488b,3888207914">喜欢</d><d p="78.64300,1,25,14811775,1507812475,0,36a36064,3888301458">Time after Time</d><d p="167.50600,1,25,14811775,1507812519,0,36a36064,3888305334">迷宫的十字路口！！</d><d p="188.03300,1,25,14811775,1507812615,0,36a36064,3888306407">银翼的魔术师</d><d p="234.79700,1,25,14811775,1507812615,0,36a36064,3888309192">啊啊啊啊啊啊沉默的十五分钟！！</d><d p="52.91700,1,25,16777215,1507971139,0,9c56e858,3892818257">纯黑的噩梦才好看</d><d p="44.71800,1,25,16777215,1508034745,0,d71f7417,3895125156">l那我要兰吧</d><d p="34.55700,1,25,16777215,1508057819,0,2b794787,3896325633">向日葵</d><d p="51.17700,1,25,16777215,1508058040,0,2b794787,3896326723">m1</d><d p="68.38500,1,25,16777215,1508058059,0,2b794787,3896327599">m2</d><d p="85.54200,1,25,16777215,1508058082,0,2b794787,3896328699">瞳孔中的暗杀者</d><d p="239.08800,1,25,16777215,1508068352,0,f9ca2057,3896813284">大爱啊。。。。。</d><d p="155.58000,1,25,15138834,1508412537,0,c0d4154,3904840774">贝克尔街的亡灵。</d><d p="234.70600,4,25,41194,1508483192,0,ef48816e,3906416789">沉默的十五分钟</d><d p="1.07200,1,25,16777215,1508549225,0,ad5b515,3908248153">。。开口跪</d><d p="21.43500,1,25,16777215,1508549464,0,ad5b515,3908249071">在柯南世界过一年得二十年</d><d p="117.56600,1,25,16777215,1508549548,0,ad5b515,3908251738">基德让我们再看了二十年柯南。。。</d><d p="151.69900,1,25,16777215,1508549574,0,ad5b515,3908253093">贝克街亡灵最好看</d><d p="196.11900,1,25,16777215,1508549583,0,ad5b515,3908255086">这个剧场毛利大叔特别帅!!!</d><d p="163.80000,5,25,16777215,1508583170,0,f298ac70,3909736100">平次平次平次平次平次平次平次平次平次平次平次平次</d><d p="121.54300,1,25,16777215,1508684567,0,8c931fcb,3913834069">唐红最后算是致敬这部了吧</d><d p="34.32300,1,25,16777215,1508685593,0,5bfe7417,3913892424">柯南毕没毕业我不知道，小雪应该毕了</d><d p="258.72500,1,25,16777215,1508860234,0,f87ba3e2,3917683838">每年暑假都会重温一遍</d><d p="190.04600,1,25,16777215,1508878733,0,75ac3361,3917896799">银翼</d><d p="239.21800,1,25,16777215,1508878781,0,75ac3361,3917896941">这里哭死</d><d p="71.37900,1,25,16777215,1508912278,0,2c7be165,3918352574">好感动</d><d p="282.04300,1,25,16777215,1508912704,0,2c7be165,3918359612">新兰永恒</d><d p="267.45900,1,25,16777215,1508943713,0,a9977ce9,3919353347">异次元的狙击手</d><d p="93.97800,1,25,15138834,1509023796,0,caa4cc9,3920874421">靠，船直接飞起666</d><d p="242.58600,1,25,15138834,1509023953,0,caa4cc9,3920880641">原画啊啊啊</d><d p="60.53000,1,25,16777215,1509078422,0,31883a8f,3921817448">不行，服部是我的</d><d p="162.51400,1,25,16777215,1509086702,0,7889254a,3922060554">前面是推理番后面是动作片</d><d p="154.86000,1,25,16777215,1509105458,0,b6ce261a,3922719936">bgm  麻衣的time of time</d><d p="48.22000,1,25,16777215,1509170704,0,fdc6a347,3924680272">光是前奏就泪奔了</d><d p="117.48900,1,25,16777215,1509235773,0,10692d1a,3926838163">kid出现</d><d p="167.94600,1,25,16777215,1509235842,0,10692d1a,3926839480">前面那个说后几部没质量的你可以滚了</d><d p="159.89100,1,25,16777215,1509451878,0,c3d2b4ee,3932636699">贝克街亡灵剧情真的不错</d><d p="127.40500,1,25,16777215,1509703617,0,885afe6c,3937955749">承包哀</d><d p="194.43300,1,25,16777215,1509703865,0,1234206e,3937965460">这局的毛利最carry</d><d p="0.74200,1,25,16777215,1509795578,0,84b8e58,3941117357">我初中也竟在看这个，然后上了我们省最好的高中</d><d p="56.97000,1,25,16777215,1509843614,0,c4f3e391,3942551089">有人看过21吗？我看了哈哈哈</d><d p="201.63500,1,25,15138834,1509899388,0,761fcbd3,3945204890">大爱这个画面！</d><d p="26.94100,5,25,41194,1510140501,0,9570c795,3950294972">柯南柯南我男神！！！</d><d p="2.49800,5,25,41194,1510140508,0,9570c795,3950295208">柯南柯南我男神！！！</d><d p="3.49800,5,25,41194,1510140428,0,9570c795,3950295425">柯南柯南我男神，</d><d p="4.49800,5,25,41194,1510140520,0,9570c795,3950295678">柯南柯南我男神！，</d><d p="39.93700,5,25,41194,1510140559,0,9570c795,3950297179">柯南柯南</d><d p="42.53800,5,25,41194,1510140586,0,9570c795,3950298277">南神！！！南神！！！</d><d p="250.26000,1,25,16777215,1510366540,0,ba748c83,3955573761">这里的滑板技术是真的6</d><d p="54.29700,5,25,16777215,1510487676,0,3ce77a5,3960062326">新一:死也要死在一起</d><d p="11.77200,1,25,16777215,1510746104,0,1cb39998,3966126173">左上角格外快????</d><d p="232.10400,1,25,16777215,1511033447,0,1fcfb33b,3973992581">沉默的十五分钟</d><d p="70.34700,1,25,16777215,1511110037,0,9e96ccb4,3976789443">帅炸了这里</d><d p="169.25200,1,25,16777215,1511110158,0,9e96ccb4,3976792490">我平次! ! !</d><d p="219.60400,1,25,16777215,1511110214,0,9e96ccb4,3976793887">兰这里超帅的!</d><d p="53.07800,1,25,16777215,1511327106,0,9c64ee21,3980992412">一听bgm就出鸡皮疙瘩</d><d p="188.17200,1,25,16777215,1511327322,0,9c64ee21,3980999332">啊啊啊喜欢银翼的魔术师</d><d p="69.74500,1,25,16777215,1511671787,0,13b2926,3989605877">从小学二年级到高中的执念啊</d><d p="157.03900,1,25,16777215,1512045540,0,1218571f,4000766027">小时候的回忆呀！</d><d p="65.46100,1,25,16777215,1512275002,0,1ad8bd70,4009797909">这里超帅</d><d p="87.72400,1,25,16777215,1512275068,0,1ad8bd70,4009801340">我喜欢你，比世界上的任何一个人都要喜欢你</d><d p="174.28400,1,25,16777215,1512275201,0,1ad8bd70,4009808178">新兰</d><d p="196.48300,1,25,16777215,1512275161,0,1ad8bd70,4009811287">毛利因为英里潜能大爆发</d><d p="205.20400,1,25,16777215,1512275283,0,1ad8bd70,4009812402">超感动</d><d p="235.16400,1,25,16777215,1512275327,0,1ad8bd70,4009814611">沉默的十五分钟</d><d p="95.38200,1,25,16777215,1512816178,0,a06bc044,4024165454">我喜欢你</d><d p="2.64500,1,25,16777215,1512892047,0,e558c7a2,4026835035">开头bgm是m13的开头吧</d><d p="260.42100,1,25,16777215,1512908198,0,3fe532e,4027542491">最喜欢的歌了，没有之一</d><d p="200.01600,1,25,16777215,1512930442,0,75f03f65,4028443296">绀碧之馆</d><d p="165.88200,5,25,16777215,1513000381,0,f0bbd28d,4029920904">迷宫的十字路口！</d><d p="188.83600,5,25,16777215,1513000414,0,f0bbd28d,4029922441">银翼的魔术师</d><d p="261.96700,5,25,16777215,1513000501,0,f0bbd28d,4029926456">异次元的狙击手</d><d p="57.03900,1,25,16777215,1513266725,0,2dbc7c15,4035847887">不能同生我们就共死</d><d p="241.04800,1,25,16777215,1513404936,0,877847e,4039108738">沉默的十五分</d><d p="193.09600,1,25,16777215,1513407416,0,208ae011,4039208627">小五郎叔叔智商上线</d><d p="260.76000,1,25,16777215,1513414558,0,b4662363,4039477835">我秀！！！</d><d p="55.20200,1,25,16777215,1513428691,0,c0611945,4040151991">。虐</d><d p="194.38100,1,25,16777215,1513428834,0,c0611945,4040159609">大叔！！！</d><d p="201.22100,1,25,16777215,1513428850,0,c0611945,4040160426">兰园闺蜜组第一</d><d p="26.19100,1,25,16777215,1513484963,0,7f915fb7,4041801453">只要1.5倍世界都开阔了</d><d p="149.26000,1,25,16777215,1513500574,0,baaf5c8c,4042501419">最喜欢的剧场版没有之一</d><d p="195.72700,1,25,16777215,1513528277,0,5117377f,4043737091">毛利叔叔超帅啊这里</d><d p="75.44300,1,25,16777215,1514017092,0,f74e8a13,4054512958">帅死了</d><d p="55.79700,1,25,16777215,1514652809,0,348b9ed1,4143203983">不能同生我们就共死</d><d p="208.82600,1,25,16777215,1514653243,0,348b9ed1,4143217606">绀碧之棺</d><d p="250.77700,1,25,16777215,1514653348,0,348b9ed1,4143221871">第十一个前锋</d><d p="266.69700,1,25,16777215,1514653378,0,348b9ed1,4143223080">这是天空的破难船吧</d><d p="12.50600,1,25,16777215,1515160868,0,f5b80a98,4158547322">柯南我男神</d><d p="51.32700,1,25,16777215,1515161240,0,f5b80a98,4158549548">基德有啥好喜欢的，我就喜欢我家新一</d><d p="186.81000,1,25,16777215,1515161267,0,f5b80a98,4158558206">突然插入怪盗??</d><d p="185.36500,1,25,16777215,1515252641,0,dcb400c,4161846624">基德我的不服来战！！</d><d p="171.47600,1,25,16777215,1515475617,0,11c610c8,4168285648">最喜欢的一部</d><d p="17.18200,1,25,16777215,1515920564,0,3dba5666,4180907894">新兰永恒</d><d p="30.34800,5,25,16777215,1516441218,0,be34e801,4195762633">日狗的向日葵</d><d p="55.19300,1,25,16777215,1516529648,0,80eadec,4198864675">这首歌，超爱的</d><d p="46.20200,1,25,16777215,1516534058,0,5babf1d1,4199049590">承包麻衣Time after time????????????</d><d p="51.18100,1,25,41194,1516534098,0,5babf1d1,4199051330">表白麻衣</d><d p="55.20000,1,25,41194,1516534137,0,5babf1d1,4199053007">大爱Time After Time????????</d><d p="63.48200,1,25,41194,1516534200,0,5babf1d1,4199055722">前面的才不是secret love，虽然都是麻衣唱的</d><d p="85.70100,1,25,41194,1516534237,0,5babf1d1,4199057263">m3 哪去了</d><d p="276.31600,1,25,41194,1516534487,0,5babf1d1,4199068767">m10,m12,m14呢</d><d p="279.31100,1,25,41194,1516534595,0,5babf1d1,4199073434">雖說現在的劇場版沒之前的做的好，但我也會一直看下去的</d><d p="261.22100,1,25,15138834,1516725752,0,f7fbf976,4207968584">啊啊啊啊啊啊啊秀一！！</d><d p="122.39600,1,25,16777215,1517043307,0,5f277787,4218315067">Bgm是贝克街的亡灵的片尾</d><d p="265.48300,1,25,16777215,1517043450,0,5f277787,4218322017">我要这硬币有何用</d><d p="281.16300,1,25,16777215,1517043465,0,5f277787,4218322772">诺诺，硬币都给你</d><d p="26.54700,1,25,16777215,1517124851,0,514c2cee,4221527635">原来如此，最精彩的就是开头bgm了！</d><d p="166.00200,1,25,41194,1517212212,0,7dab77f2,4224767707">最喜欢的没有之一！就是这部入坑的</d><d p="118.00500,1,25,16777215,1517910970,0,981f0a2e,4267600413">通往天国的倒计时</d><d p="78.26100,1,25,16777215,1518152620,0,a563491b,4278724583">新兰永恒！</d><d p="84.18100,1,25,16777215,1518152656,0,a563491b,4278726505">无论等多久，我都会一直等你……</d><d p="252.22000,1,25,16777215,1518152833,0,a563491b,4278736478">想哭啊！</d><d p="265.76000,1,25,16777215,1519043024,0,69782190,4318936807">业火的向日葵！</d><d p="36.16200,1,25,16777215,1519131341,0,3249a4c6,4324514851">唐红的恋歌</d><d p="182.03900,1,25,16777215,1520078381,0,ec1cec04,4362217502">迷宫的十字路口</d><d p="214.42600,1,25,16777215,1520599665,0,cbe2aa43,4375640031">幸亏早早把所以剧场版资源都保存了</d><d p="45.08800,1,25,16777215,1528200818,0,f3c85c4a,555034071793666">引爆摩天楼</d><d p="65.38900,1,25,16777215,1530892334,0,1e2a861d,1966163529039872">always! </d><d p="5.10000,1,25,16777215,1531824918,0,89ea8df8,2455106003927044">BGN战栗的乐谱</d><d p="5.10000,1,25,16777215,1531824927,0,89ea8df8,2455110952681476">前面的BGM</d><d p="1.61700,1,25,16777215,1531824985,0,89ea8df8,2455141641879552">封面是 天空的遇难船？</d><d p="179.63600,1,25,16777215,1531893420,0,d57c6ae1,2491021297975360">平新</d><d p="39.76500,1,25,16777215,1532312119,0,52d02ba3,2710539912347652">前面的 服部是我的！</d><d p="162.98600,1,25,16777215,1532312252,0,52d02ba3,2710609458626562">平和！！</d><d p="168.93600,1,25,16777215,1532507820,0,be4b04a,2813143735074816">平和啊</d><d p="22.17300,1,25,16777215,1532841797,0,e1a9a18b,2988243672891396">绝海的侦探</d><d p="34.45600,1,25,16777215,1532841822,0,e1a9a18b,2988256923222016">异次元的狙击手 业火的向日葵！</d><d p="10.65300,1,25,16777215,1532931065,0,2888f687,3035046101385216">封面是m16第十一个前锋</d><d p="50.96300,1,25,14811775,1532931127,0,2888f687,3035078426361858">m1引爆摩天大楼</d><d p="266.97200,1,25,16777215,1532939018,0,2888f687,3039215691497476">喂喂，绝海的侦探呢！</d><d p="273.63900,1,25,16707842,1532939053,0,2888f687,3039233818755072">镇魂歌呢？乐谱呢？绝海呢？</d><d p="82.08400,1,25,16777215,1533279515,0,a51d2129,3217733987598336">我已经要哭了</d><d p="15.25200,1,25,16777215,1533614270,0,c3c9ee84,3393241939968002">不，封面是第11位前锋</d><d p="96.08600,1,25,16777215,1533661404,0,e2ab9d61,3417953709064196">BGM是什么</d><d p="114.14800,1,25,16777215,1533696244,0,a5b608e5,3436220004171780">基德怒刷存在感</d><d p="263.27500,5,25,16707842,1533739912,0,91ae635b,3459114846912512">向日葵</d><d p="160.20300,1,25,16777215,1533780772,0,32ffeba3,3480537096257536">贝克街的亡灵</d><d p="132.85000,1,25,16777215,1534235409,0,e4ea076e,3718897539219456">通往天国的倒计时</d><d p="236.61700,1,25,16777215,1534235516,0,e4ea076e,3718953756000256">哭了</d><d p="52.15900,1,25,16777215,1534313672,0,70926f0e,3759930180370432">剧场版和BGM不搭啊</d><d p="42.40000,1,25,16707842,1534393036,0,d90c88ab,3801539920527364">坐等22零的审判</d><d p="60.00100,1,25,16777215,1534653212,0,6f14e133,3937946910064644">真的哭了，这首歌感人</d><d p="175.21800,1,25,16777215,1534653349,0,6f14e133,3938018423472128">兰抱着柯南跳下那个大楼那段真的感人</d><d p="151.78500,1,25,16777215,1534684376,0,e3590640,3954285699661828">贝克街的亡灵</d><d p="233.72800,1,25,16777215,1534684497,0,e3590640,3954349350322176">最爱最爱！</d><d p="266.84000,1,25,16777215,1534684552,0,e3590640,3954377976446976">业火的向日葵</d><d p="43.18700,1,25,16777215,1534923504,0,b2e665a4,4079657481666560">第八副向日葵</d><d p="165.45400,1,25,16777215,1534923930,0,b2e665a4,4079881242017792">开膛手杰克</d><d p="60.56500,1,25,16777215,1534951682,0,25e898f7,4094430963826688">哇我刚看完迷宫的十字路口！bgm是它的ed</d><d p="207.16700,1,25,16777215,1534951839,0,25e898f7,4094513331568644">“把我的背后交给你”</d><d p="283.34200,1,25,16777215,1534956245,0,25e898f7,4096823530618880">感谢几年来的陪伴</d><d p="201.98300,1,25,16777215,1534956552,0,25e898f7,4096984270503936">把我的背后交给你”</d><d p="210.51700,1,25,16777215,1534956566,0,25e898f7,4096991495716864">哭了</d><d p="277.93000,1,25,16777215,1534956835,0,25e898f7,4097132675989508">要回顾的 优酷有啊！</d><d p="282.19700,1,25,16777215,1535030175,0,25e898f7,4135583841517572">感谢这么多年的陪伴</d><d p="179.14400,1,25,16777215,1535180290,0,893d0701,4214287614607362">m6最精彩的应该是兰跳崖</d><d p="282.40000,1,25,16777215,1535180414,0,893d0701,4214352545054720">你不要告诉我缺的剧场版没有精彩片段</d><d p="65.34000,1,25,16777215,1535635603,0,f0df9a3a,4453002924523520">天啊想想我喜欢新一已经15年了</d><d p="3.29900,1,25,16777215,1535642652,0,b1ef8603,4456698289848320">封面是：名侦探柯南剧场版，第十一人的前锋</d><d p="99.20000,1,25,16777215,1535672229,0,7b2cffb6,4472205430226948">因为喜欢你</d><d p="109.20000,1,25,16777215,1535672243,0,7b2cffb6,4472212551106564">世纪末的魔术师</d><d p="121.84100,1,25,16777215,1535672259,0,7b2cffb6,4472220923985924">天国倒计时</d><d p="147.36000,1,25,16777215,1535672313,0,7b2cffb6,4472249308938244">这个很赞  贝克街亡灵</d><d p="193.76000,1,25,16777215,1535672373,0,7b2cffb6,4472280461606916">水平线阴谋</d><d p="183.64000,1,25,16777215,1535672356,0,7b2cffb6,4472271502049280">银翼魔术师</d><d p="244.12000,1,25,16777215,1535672447,0,7b2cffb6,4472319709806596">第11前锋</d><d p="213.96000,1,25,16777215,1535672412,0,7b2cffb6,4472300945539072">这个应该选琴酒震惊的那一点吧</d><d p="156.52600,1,25,16777215,1535901485,0,3279014,4592401131241472">time after time</d><d p="97.65900,1,25,16777215,1535914831,0,ad177125,4599398504857600">万能夏威夷</d><d p="54.21800,1,25,16777215,1536073919,0,bf8b81eb,4682806377578500">呜呜呜呜呜</d><d p="15.33200,1,25,16777215,1536073881,0,bf8b81eb,4682786021048322">吓死我！！！！！</d><d p="6.80700,1,25,16777215,1536324140,0,c124f2e0,4813994474864644">封面m16，最后解决爆炸那里，踢任意球那吧</d><d p="6.49900,5,25,16777215,1536327442,0,edc9f03f,4815725372899330">蓝色的，不要和我争</d><d p="32.94500,1,25,16777215,1536684703,0,2767944c,5003032914296836">因为我不想剪断我和新一的红线</d><d p="160.18400,1,25,16777215,1536685037,0,2767944c,5003208171716608">浑身浴血</d><d p="151.01300,1,25,16777215,1536760582,0,bad59d66,5042815669633024">贝克街吹爆</d><d p="58.58100,1,25,16777215,1536925751,0,348b9ed1,5129411630727170">平和一生推！</d><d p="113.18200,1,25,16777215,1536925816,0,348b9ed1,5129446004621312">基德来还人情了2333</d><d p="205.91900,1,25,16777215,1536925964,0,348b9ed1,5129523554156546">看到这就想起刺客信条黑旗 安妮和玛丽。。唉  玛丽死的时候真的泪目  通关三遍心里难受三遍</d><d p="235.14700,1,25,16777215,1536969201,0,34c0902f,5152192044990468">爱</d><d p="50.39000,1,25,16777215,1537000710,0,ca45253,5168711957741572">m1</d><d p="61.40100,1,25,16777215,1537000724,0,ca45253,5168719262121988">m2</d><d p="185.01300,1,25,16777215,1537000868,0,ca45253,5168794799439872">银翼的魔术师</d><d p="156.64900,1,25,16777215,1537000833,0,ca45253,5168776587247620">前七部经典</d><d p="244.58300,1,25,16777215,1537000943,0,ca45253,5168833903984640">战栗的乐谱没有</d><d p="241.52200,1,25,16777215,1537187963,0,3bee9957,5266886178635780">一样</d><d p="153.82100,1,25,16777215,1537192182,0,14b2f03e,5269098570186756">最爱的 贝克街的亡灵了！！！！</d><d p="152.83300,1,25,16777215,1537370006,0,7ae16015,5362329400115200">最爱贝克街</d><d p="234.00900,1,25,16777215,1537370104,0,7ae16015,5362380496175108">柯哀来了！</d><d p="47.04100,1,25,16777215,1537575791,0,b7f7f3f8,5470220154044416">日狗的向日葵</d><d p="148.64600,1,25,16777215,1537593941,0,154b9a8c,5479735548182528">贝克街的亡灵</d><d p="260.50700,5,25,16777215,1537613072,0,e55c083c,5489765795758080">秀一</d><d p="276.10200,1,25,16777215,1537673078,0,a78c3bdd,5521226162765828">每一部都是经典</d><d p="24.59900,1,25,16777215,1537752507,0,1f9543ec,5562869774548992">激动\(≧▽≦)/</d><d p="74.98300,1,25,16777215,1537806591,0,71319535,5591225670303744">等着零的执行人出场</d><d p="149.66000,1,25,16777215,1537806676,0,71319535,5591270044467204">贝克街的亡灵</d><d p="164.26000,1,25,16777215,1537806706,0,71319535,5591285838643200">迷宫的十字路</d><d p="187.90000,1,25,16777215,1537806743,0,71319535,5591305463791618">银翼的魔术师</d><d p="196.10000,1,25,16777215,1537806765,0,71319535,5591316841889792">水平线上的阴谋</d><d p="128.21000,1,25,16777215,1537941018,0,5b27a18c,5661704024227844">元太也很帅的好么！这里是他把灰原抱上车的！</d><d p="55.21800,1,25,16777215,1537942533,0,2054acad,5662498580594688">起鸡皮疙瘩了</d><d p="122.92200,1,25,16777215,1537942601,0,2054acad,5662534044483584">通往天国的倒计时</d><d p="147.93200,1,25,16777215,1537942793,0,2054acad,5662634609213440">贝克街~！</d><d p="186.81100,1,25,16777215,1537942833,0,2054acad,5662655771574276">银翼</d><d p="211.09100,1,25,16777215,1537942857,0,2054acad,5662668462489602">漆黑</d><d p="241.69100,1,25,16777215,1537942888,0,2054acad,5662684539256834">沉默</d><d p="197.59500,1,25,16777215,1537942844,0,2054acad,5662661422874628">水平线！</d><d p="203.71500,1,25,16777215,1537942850,0,2054acad,5662664630468612">绀碧之棺</d><d p="163.61500,5,25,16777215,1538307232,0,8a925ba7,5853705871032320">主场</d><d p="96.02000,5,25,16777215,1538492468,0,11c420aa,5950822585729024">因为喜欢你啊，比世界上任何一个人都喜欢</d><d p="148.91900,5,25,16777215,1538492528,0,11c420aa,5950853897781250">贝克街的亡灵</d><d p="163.31900,5,25,16777215,1538492549,0,11c420aa,5950864946102272">迷宫的十字路口</d><d p="200.05900,5,25,16777215,1538492597,0,11c420aa,5950890111401988">绀碧之棺</d><d p="213.17900,5,25,16777215,1538492615,0,11c420aa,5950899792379904">漆黑的追踪者</d><d p="232.91900,5,25,16777215,1538492644,0,11c420aa,5950914757656576">沉默的十五分钟</d><d p="264.43900,5,25,16777215,1538492687,0,11c420aa,5950937351847938">业火的向日葵</d><d p="262.70600,5,25,16777215,1538492699,0,11c420aa,5950943629672448">业火的向日葵</d><d p="49.01900,1,25,16777215,1538549483,0,ffa7e39,5980715068424194">引爆摩天楼</d><d p="57.61900,1,25,14811775,1538549513,0,ffa7e39,5980730707935232">新兰啊啊啊啊，新兰大旗我来扛</d><d p="200.57900,1,25,14811775,1538549688,0,ffa7e39,5980822471966720">兰园大法好！</d><d p="163.93900,1,25,14811775,1538549642,0,ffa7e39,5980798481072128">迷宫的十字路口</d><d p="238.55900,1,25,14811775,1538549737,0,ffa7e39,5980848296820736">沉默的十五分钟</d><d p="249.81900,1,25,14811775,1538549761,0,ffa7e39,5980860588228608">第十一个先锋</d><d p="61.19800,1,25,16777215,1538582213,0,89508442,5997874759860226">新一男神啊</d><d p="166.21400,1,25,16707842,1538582338,0,89508442,5997940197294080">新一是我的我的阿阿阿</d><d p="45.89000,1,25,15138834,1540390246,0,2fecdcfa,6945804931563520">举起我快新大旗</d><d p="39.63400,1,25,16777215,1540616775,0,6f11df69,7064571171831808">基德我的</d><d p="181.94900,1,25,16777215,1540616924,0,6f11df69,7064649285500928">基德啊啊啊啊啊啊</d><d p="260.66400,1,25,16777215,1540617033,0,6f11df69,7064706593325056">赤井帅炸</d><d p="59.40800,1,25,16777215,1541079891,0,f06e87d9,7307377529323522">第十四个目标</d><d p="238.33900,1,25,16777215,1541317051,0,95f7eade,7431717410832386">最爱啊！</d><d p="5.87300,1,25,16777215,1541507948,0,c8c49826,7531802919436288">封面是第十一人的前锋</d><d p="99.54700,1,25,16777215,1541999381,0,be7925db,7789455220932608">入二次元神曲</d><d p="273.24300,1,25,16777215,1542031431,0,d63fb30a,7806258598903808">牛顿的眼泪</d><d p="36.05400,1,25,16777215,1542082635,0,c2c4b5c5,7833104217014272">毕业的时候我会烧给你看的</d><d p="53.50100,1,25,16777215,1542101417,0,569f2e61,7842951318732800">画质好差</d><d p="78.37000,1,25,16777215,1542101455,0,569f2e61,7842971325562880">嘴呢</d><d p="56.95000,1,25,16777215,1542213526,0,a9739229,7901728533905408">time after time</d><d p="101.34900,1,25,16777215,1542247592,0,33f2daf6,7919589401296896">唯一一次不想基德出来</d><d p="42.67200,1,25,16777215,1542432458,0,624c078c,8016512102170624">QAQ画质感人</d><d p="132.35300,1,25,16777215,1542433648,0,6c782ae0,8017136291151872">明明是后宫</d><d p="28.83600,1,25,16777215,1542457584,0,534f3cc8,8029685313699840">异次元的狙击手超爱的啊</d><d p="235.63500,1,25,16777215,1542471789,0,d8589f40,8037133151371266">m10侦探们的镇魂曲呢</d><d p="29.56000,1,25,16777215,1542472778,0,8a4dfba5,8037651441516608">业火的向日葵</d><d p="23.92200,1,25,16777215,1542472763,0,8a4dfba5,8037643647975424">异次元的狙击手</d><d p="74.21000,1,25,16777215,1542472844,0,8a4dfba5,8037685905063936">第十四个目标</d><d p="111.85000,1,25,16777215,1542472904,0,8a4dfba5,8037717340848128">基德大人</d><d p="149.72100,1,25,16777215,1542473003,0,8a4dfba5,8037769446162432">贝克街的亡灵</d><d p="118.42100,1,25,16777215,1542472946,0,8a4dfba5,8037739568562176">通往天国的倒计时</d><d p="164.02500,1,25,16777215,1542473030,0,8a4dfba5,8037783641260032">迷宫的十字路口</d><d p="182.04300,1,25,16777215,1542473064,0,8a4dfba5,8037801549889536">基德大人</d><d p="196.27400,1,25,16777215,1542473124,0,8a4dfba5,8037832591933440">水平线上的阴谋，我看的第二部电影在小学</d><d p="202.47700,1,25,16777215,1542473165,0,8a4dfba5,8037854120247296">绀碧之馆</d><d p="234.08100,1,25,16777215,1542473253,0,8a4dfba5,8037900570066944">第三部看的，沉默的十五分钟</d><d p="234.52000,1,25,16777215,1542473301,0,8a4dfba5,8037925604294658">雪灾的黄金时间是十五分钟</d><d p="265.19400,1,25,16777215,1542473341,0,8a4dfba5,8037946647642112">业火的向日葵</d><d p="220.89200,1,25,16777215,1542545932,0,cb5b5dc5,8076005141381120">人比枪快记忆最深</d><d p="64.71000,1,25,16777215,1542710788,0,d66d15ab,8162437479530498">bgm我们高中学校放学铃声 呜呜呜</d><d p="267.76900,1,25,16777215,1542717081,0,8545d1e2,8165736403959808">R狗的向日葵..</d><d p="18.76100,1,25,16777215,1542796211,0,ec127f1a,8207223480647682">封面好眼熟</d><d p="103.58400,1,25,16777215,1542796289,0,ec127f1a,8207264390840320">太赞了</d><d p="84.45300,1,25,16777215,1542814226,0,a36b32,8216668607086592">每一部都是回忆啊</d><d p="156.43600,1,25,16777215,1542814311,0,a36b32,8216713230286848">贝克街的亡灵超好看的</d><d p="62.96700,1,25,16777215,1543226314,0,ac2199,8432721210638336">前奏泪奔</d><d p="7.04000,1,25,16777215,1543294280,0,6b752d95,8468354876047360">封面：第11个前锋</d><d p="32.36000,1,25,16777215,1543294313,0,6b752d95,8468372311244800">新机子哇一自摸黑多次</d><d p="58.47300,1,25,16777215,1543317992,0,bf9a707c,8480786894290944">小学的时候看这里真的哭了</d><d p="41.72400,1,25,16765698,1543319689,0,4f873fbb,8481676850102272">弱弱问一句灰原可以抱走吗</d><d p="78.60200,1,25,16765698,1543319764,0,4f873fbb,8481715807846400">我在夏威夷学的徒手拆高达</d><d p="44.83700,1,25,16777215,1543550464,0,bbb400b,8602669159546880">第十一个前锋!</d><d p="114.98500,1,25,16777215,1543550534,0,bbb400b,8602705934155778">基德</d><d p="79.84700,1,25,16777215,1543550499,0,bbb400b,8602687650660354">kiss!</d><d p="161.18700,1,25,16777215,1543550580,0,bbb400b,8602730170941504">充满讽刺...</d><d p="156.24000,1,25,16777215,1543672001,0,3f2905ff,8666389793472512">这个真的棒</d><d p="2.78500,5,25,15138834,1543685582,0,60f92567,8673510188122112">封面是第11个前锋，m16</d><d p="54.43400,1,25,16777215,1544061752,0,59177eb1,8870731284217856">追了15年</d><d p="156.44400,1,25,16777215,1544454202,0,521fa4a4,9076488135507968">这个真的超好看</d><d p="157.80200,1,25,16777215,1544852437,0,8f37cfae,9285278266032128">最爱</d><d p="116.66400,1,25,16777215,1544942146,0,e4047b46,9332311657021440">这不来了吗</d><d p="264.94100,1,25,16777215,1544942306,0,e4047b46,9332395109515264">绝海的侦探呢？</d><d p="276.05900,1,25,16777215,1545041671,0,45289d35,9384491185340416">战栗的乐谱呢</d><d p="285.29300,1,25,16777215,1545069057,0,d4d2d84e,9398849607041024">这部真的快看哭了</d><d p="47.08300,1,25,16777215,1545303595,0,dc38ad0d,9521815015653376">看了回来</d><d p="0.27700,1,25,16777215,1545495059,0,375a90f6,9622197269168128">封面…第十一个前锋</d><d p="40.52800,1,25,16777215,1545517731,0,afd908cc,9634083671375872">业火的向日葵里有基德，强烈推荐</d></i>