<?xml version="1.0" encoding="UTF-8"?><i><chatserver>chat.bilibili.com</chatserver><chatid>6533684</chatid><mission>0</mission><maxlimit>8000</maxlimit><state>0</state><real_name>0</real_name><source>e-r</source><d p="75.05200,1,25,16777215,1457456486,0,6b0dc180,1668580173">百度毒瘤啊</d><d p="538.73700,1,25,16777215,1457456504,0,6b0dc180,1668596189">这个应该是最流行的了吧</d><d p="631.78500,1,25,16777215,1457456506,0,6b0dc180,1668597983">google就是搞太多东西 之后好多又停了 比如docs</d><d p="865.47700,1,25,16777215,1457456510,0,6b0dc180,1668601435">知乎上有讨论贴</d><d p="1515.40000,1,25,16777215,1457460121,0,6b0dc180,1668609295">学习了</d><d p="12.95000,1,25,16777215,1457460135,0,db7fbf58,1668619353">第一</d><d p="202.52400,1,25,16777215,1457496767,0,a6f03a13,1668909375">才发现好长的视频</d><d p="872.84000,1,25,16777215,1457503364,0,2cace6e4,1669109005">抓走了  默哀</d><d p="119.26700,1,25,16777215,1457506988,0,8e4dcef1,1669136163">23333</d><d p="4590.53400,1,25,16777215,1505264984,0,c96f7167,3808220132">50M以上不让下载</d></i>