<?xml version="1.0" encoding="UTF-8"?><i><chatserver>chat.bilibili.com</chatserver><chatid>6533725</chatid><mission>0</mission><maxlimit>1000</maxlimit><state>0</state><real_name>0</real_name><source>e-r</source><d p="29.13900,1,25,16777215,1457532620,0,6e6935b5,1670103105">我来看我男神高桥小哥~</d><d p="44.53800,1,25,16777215,1457546578,0,4b36f1ee,1670627413">但這部日劇實在是很沒有內容 完全就是賣龜梨和也的感覺</d><d p="96.72300,1,25,16777215,1457546579,0,4b36f1ee,1670627753">總是就是大家來比賽</d><d p="136.36700,1,25,16777215,1457583158,0,875dae61,1670970255">一，500元硬币 二，大碗牛肉盖饭 三，刚出生的婴儿</d><d p="246.99000,1,25,16777215,1457583160,0,875dae61,1670975429">问题二：食品成分表里面卡路里最低的是哪个</d><d p="249.90600,1,25,16777215,1457583165,0,875dae61,1670986549">一，魔芋 二，生香菇 三，海发菜</d><d p="319.64700,1,25,16777215,1457604390,0,3e55c5c7,1671828529">卡咩23333</d><d p="0.00000,1,25,10092492,1457931665,0,f679b79f,1681520529">先马！！感谢Up主！！！</d><d p="307.19300,1,25,13434726,1457950001,0,f679b79f,1682037365">这些题怎么难得倒我桥呢~~</d><d p="17.05700,5,25,16777215,1458742222,0,f658101,1702303135">低调承包我桥w</d><d p="52.52300,1,25,16777215,1459123704,0,25fbd4be,1712725557">前面你有看过这部高桥的原著漫画？</d><d p="25.72700,1,25,16777215,1463907909,0,968c2b6c,1873962899">又不看镜头</d><d p="311.65800,1,25,16777215,1463907914,0,968c2b6c,1873981001">前面的说的好！</d><d p="57.70300,1,25,16777215,1467626765,0,869c452,2036196941">好帅嘤嘤嘤</d><d p="345.49400,1,25,16777215,1467626770,0,869c452,2036219069">好可爱呀。。。</d><d p="145.97100,1,25,16777215,1470496261,0,aaf3bb9f,2218630557">这笑看了好多遍</d><d p="79.92300,1,25,16777215,1473573737,0,f79d0ea7,2395301083">小哥在一群人中越发显得清秀啊</d><d p="36.64100,1,25,16777215,1475946088,0,f79d0ea7,2529291177">总觉得这个时候属于小哥颜值巅峰</d><d p="37.98700,1,25,16777215,1482555696,0,f79d0ea7,2776914643">好帅</d></i>