<?xml version="1.0" encoding="UTF-8"?><i><chatserver>chat.bilibili.com</chatserver><chatid>6537667</chatid><mission>0</mission><maxlimit>1000</maxlimit><state>0</state><real_name>0</real_name><source>e-r</source><d p="85.86300,1,25,16777215,1457514324,0,5c8f8d7c,1669466977">消灭零弹幕！！！！！！</d><d p="63.24000,1,25,65535,1457514326,0,3ad717cb,1669470155">夏目小天使QAQ</d><d p="145.23700,5,25,16711680,1457514327,0,3ad717cb,1669471231">NO Blood ! No Bone ! No Ash !</d><d p="44.35500,1,25,16777215,1457514339,0,37e848a6,1669490295">此处弹幕由我承包</d><d p="126.07400,1,25,16777215,1457514340,0,37e848a6,1669492529">我开始方了</d><d p="145.31600,1,25,16777215,1457514341,0,37e848a6,1669494119">NoBlood!NoBone!NoAsh!</d><d p="250.93100,1,25,16777215,1457514343,0,37e848a6,1669497115">安娜酱</d><d p="76.46100,1,25,16777215,1457517985,0,d2f0af2b,1669582695">娘口三三 </d><d p="8.06200,1,25,16777215,1457949962,0,528ab2c,1681959837">見k滾</d><d p="227.40400,1,25,16777215,1457949988,0,da5d905a,1682010063">洛叔犯规啊</d></i>